[{"id":21,"annotations":[{"id":7,"completed_by":1,"result":[{"value":{"start":"2025-07-31T12:05:16.531000","end":"2025-07-31T12:09:13.796000","instant":false,"timeserieslabels":["load_event"]},"id":"FsZdp-Pemp","from_name":"phase","to_name":"ts","type":"timeserieslabels","origin":"manual"},{"value":{"start":"2025-07-31T12:19:46.001000","end":"2025-07-31T12:21:39.129000","instant":false,"timeserieslabels":["dump_event"]},"id":"3XtdkpEhls","from_name":"phase","to_name":"ts","type":"timeserieslabels","origin":"manual"},{"value":{"start":"2025-07-31T12:35:57.116000","end":"2025-07-31T12:41:12.980000","instant":false,"timeserieslabels":["load_event"]},"id":"5mtifvgE4i","from_name":"phase","to_name":"ts","type":"timeserieslabels","origin":"manual"},{"value":{"start":"2025-07-31T12:56:39.051000","end":"2025-07-31T12:58:20.672000","instant":false,"timeserieslabels":["dump_event"]},"id":"TFp3gx7D2m","from_name":"phase","to_name":"ts","type":"timeserieslabels","origin":"manual"},{"value":{"start":"2025-07-31T13:13:46.245000","end":"2025-07-31T13:20:21.165000","instant":false,"timeserieslabels":["load_event"]},"id":"QQqEpAALNF","from_name":"phase","to_name":"ts","type":"timeserieslabels","origin":"manual"},{"value":{"start":"2025-07-31T13:31:04.946000","end":"2025-07-31T13:32:24.038000","instant":false,"timeserieslabels":["dump_event"]},"id":"nZAfaF8qoG","from_name":"phase","to_name":"ts","type":"timeserieslabels","origin":"manual"},{"value":{"start":"2025-07-31T13:36:54.882000","end":"2025-07-31T13:41:59.707000","instant":false,"timeserieslabels":["load_event"]},"id":"kYP_acYLPr","from_name":"phase","to_name":"ts","type":"timeserieslabels","origin":"manual"},{"value":{"start":"2025-07-31T13:47:04.550000","end":"2025-07-31T13:48:23.638000","instant":false,"timeserieslabels":["dump_event"]},"id":"-0LE2fvtaz","from_name":"phase","to_name":"ts","type":"timeserieslabels","origin":"manual"},{"value":{"start":"2025-07-31T13:58:21.811000","end":"2025-07-31T14:10:35.662000","instant":false,"timeserieslabels":["load_event"]},"id":"FyskjyUNBj","from_name":"phase","to_name":"ts","type":"timeserieslabels","origin":"manual"},{"value":{"start":"2025-07-31T14:15:29.512000","end":"2025-07-31T14:17:44.665000","instant":false,"timeserieslabels":["dump_event"]},"id":"U9IX8Kjjgp","from_name":"phase","to_name":"ts","type":"timeserieslabels","origin":"manual"},{"value":{"start":"2025-07-31T14:26:06.749000","end":"2025-07-31T14:31:00.601000","instant":false,"timeserieslabels":["load_event"]},"id":"5MPBYA3jDp","from_name":"phase","to_name":"ts","type":"timeserieslabels","origin":"manual"},{"value":{"start":"2025-07-31T14:38:54.669000","end":"2025-07-31T14:41:31.855000","instant":false,"timeserieslabels":["dump_event"]},"id":"sw7WUqc5uT","from_name":"phase","to_name":"ts","type":"timeserieslabels","origin":"manual"},{"value":{"start":"2025-07-31T15:24:53.345000","end":"2025-07-31T15:29:45.196000","instant":false,"timeserieslabels":["load_event"]},"id":"CZ3cgn_Jd9","from_name":"phase","to_name":"ts","type":"timeserieslabels","origin":"manual"},{"value":{"start":"2025-07-31T15:41:09.430000","end":"2025-07-31T15:43:12.568000","instant":false,"timeserieslabels":["dump_event"]},"id":"eEmsvzlv8A","from_name":"phase","to_name":"ts","type":"timeserieslabels","origin":"manual"},{"value":{"start":"2025-07-31T15:49:56.518000","end":"2025-07-31T15:56:28.965000","instant":false,"timeserieslabels":["load_event"]},"id":"XuZ4_RLTKt","from_name":"phase","to_name":"ts","type":"timeserieslabels","origin":"manual"},{"value":{"start":"2025-07-31T16:12:11.019000","end":"2025-07-31T16:13:40.615000","instant":false,"timeserieslabels":["dump_event"]},"id":"31mIlfYj7V","from_name":"phase","to_name":"ts","type":"timeserieslabels","origin":"manual"},{"value":{"start":"2025-07-31T16:18:20.948000","end":"2025-07-31T16:24:08.326000","instant":false,"timeserieslabels":["load_event"]},"id":"vyp6PEypX7","from_name":"phase","to_name":"ts","type":"timeserieslabels","origin":"manual"},{"value":{"start":"2025-07-31T16:31:25.820000","end":"2025-07-31T16:33:06.932000","instant":false,"timeserieslabels":["dump_event"]},"id":"6Qj6vtnzKJ","from_name":"phase","to_name":"ts","type":"timeserieslabels","origin":"manual"},{"value":{"start":"2025-07-31T16:38:20.795000","end":"2025-07-31T16:45:38.278000","instant":false,"timeserieslabels":["load_event"]},"id":"IK-9oR-tGf","from_name":"phase","to_name":"ts","type":"timeserieslabels","origin":"manual"},{"value":{"start":"2025-07-31T16:55:43.986000","end":"2025-07-31T16:57:47.122000","instant":false,"timeserieslabels":["dump_event"]},"id":"Wnf6zIUbBg","from_name":"phase","to_name":"ts","type":"timeserieslabels","origin":"manual"},{"value":{"start":"2025-07-31T17:03:46.053000","end":"2025-07-31T17:10:41.018000","instant":false,"timeserieslabels":["load_event"]},"id":"xaBvIooZiT","from_name":"phase","to_name":"ts","type":"timeserieslabels","origin":"manual"},{"value":{"start":"2025-07-31T17:24:58.970000","end":"2025-07-31T17:27:00.615000","instant":false,"timeserieslabels":["dump_event"]},"id":"VYkImpMhyn","from_name":"phase","to_name":"ts","type":"timeserieslabels","origin":"manual"},{"value":{"start":"2025-07-31T17:36:04.779000","end":"2025-07-31T17:41:04.141000","instant":false,"timeserieslabels":["load_event"]},"id":"ygsav2p1sZ","from_name":"phase","to_name":"ts","type":"timeserieslabels","origin":"manual"},{"value":{"start":"2025-07-31T17:46:59.053000","end":"2025-07-31T17:49:23.723000","instant":false,"timeserieslabels":["dump_event"]},"id":"I5qUyFGGW6","from_name":"phase","to_name":"ts","type":"timeserieslabels","origin":"manual"},{"value":{"start":"2025-07-31T17:54:34.093000","end":"2025-07-31T17:59:44.979000","instant":false,"timeserieslabels":["load_event"]},"id":"SfCEI6f8TP","from_name":"phase","to_name":"ts","type":"timeserieslabels","origin":"manual"},{"value":{"start":"2025-07-31T18:06:57.506000","end":"2025-07-31T18:10:06.213000","instant":false,"timeserieslabels":["dump_event"]},"id":"_KWS2Jl7RJ","from_name":"phase","to_name":"ts","type":"timeserieslabels","origin":"manual"},{"value":{"start":"2025-07-31T18:19:43.414000","end":"2025-07-31T18:26:00.359000","instant":false,"timeserieslabels":["load_event"]},"id":"zCZWqGmk2f","from_name":"phase","to_name":"ts","type":"timeserieslabels","origin":"manual"},{"value":{"start":"2025-07-31T18:34:19.944000","end":"2025-07-31T18:36:22.080000","instant":false,"timeserieslabels":["dump_event"]},"id":"1RPBer6EaL","from_name":"phase","to_name":"ts","type":"timeserieslabels","origin":"manual"},{"value":{"start":"2025-07-31T18:49:41.051000","end":"2025-07-31T18:55:35.988000","instant":false,"timeserieslabels":["load_event"]},"id":"fT1SsCB8yT","from_name":"phase","to_name":"ts","type":"timeserieslabels","origin":"manual"},{"value":{"start":"2025-07-31T19:08:21.910000","end":"2025-07-31T19:10:35.072000","instant":false,"timeserieslabels":["dump_event"]},"id":"JiMFoKYGr-","from_name":"phase","to_name":"ts","type":"timeserieslabels","origin":"manual"},{"value":{"start":"2025-07-31T19:18:20.653000","end":"2025-07-31T19:26:06.681000","instant":false,"timeserieslabels":["load_event"]},"id":"6Vfj8pP-Og","from_name":"phase","to_name":"ts","type":"timeserieslabels","origin":"manual"},{"value":{"start":"2025-07-31T19:38:52.583000","end":"2025-07-31T19:40:32.686000","instant":false,"timeserieslabels":["dump_event"]},"id":"P384I5P0RD","from_name":"phase","to_name":"ts","type":"timeserieslabels","origin":"manual"},{"value":{"start":"2025-07-31T19:53:51.630000","end":"2025-07-31T19:59:57.542000","instant":false,"timeserieslabels":["load_event"]},"id":"TUzj02J2is","from_name":"phase","to_name":"ts","type":"timeserieslabels","origin":"manual"},{"value":{"start":"2025-07-31T20:07:58.603000","end":"2025-07-31T20:09:01.680000","instant":false,"timeserieslabels":["dump_event"]},"id":"YkNSSIi9rd","from_name":"phase","to_name":"ts","type":"timeserieslabels","origin":"manual"},{"value":{"start":"2025-07-31T20:17:19.284000","end":"2025-07-31T20:23:02.193000","instant":false,"timeserieslabels":["load_event"]},"id":"-_8YmPVN24","from_name":"phase","to_name":"ts","type":"timeserieslabels","origin":"manual"},{"value":{"start":"2025-07-31T20:33:53.954000","end":"2025-07-31T20:35:18.049000","instant":false,"timeserieslabels":["dump_event"]},"id":"dVAKsWpJiH","from_name":"phase","to_name":"ts","type":"timeserieslabels","origin":"manual"},{"value":{"start":"2025-07-31T20:43:07.136000","end":"2025-07-31T20:48:29.503000","instant":false,"timeserieslabels":["load_event"]},"id":"T2wk1AqdOS","from_name":"phase","to_name":"ts","type":"timeserieslabels","origin":"manual"},{"value":{"start":"2025-07-31T21:06:21.290000","end":"2025-07-31T21:07:38.378000","instant":false,"timeserieslabels":["dump_event"]},"id":"7VDOHUGLpL","from_name":"phase","to_name":"ts","type":"timeserieslabels","origin":"manual"},{"value":{"start":"2025-07-31T21:26:10.171000","end":"2025-07-31T21:30:50.006000","instant":false,"timeserieslabels":["load_event"]},"id":"bp1QBSuBBU","from_name":"phase","to_name":"ts","type":"timeserieslabels","origin":"manual"},{"value":{"start":"2025-07-31T21:39:14.587000","end":"2025-07-31T21:40:38.701000","instant":false,"timeserieslabels":["dump_event"]},"id":"7vAktnUpuS","from_name":"phase","to_name":"ts","type":"timeserieslabels","origin":"manual"},{"value":{"start":"2025-07-31T21:49:44.894000","end":"2025-07-31T21:54:39.222000","instant":false,"timeserieslabels":["load_event"]},"id":"HNixQPPS8i","from_name":"phase","to_name":"ts","type":"timeserieslabels","origin":"manual"},{"value":{"start":"2025-07-31T22:15:47.193000","end":"2025-07-31T22:17:18.293000","instant":false,"timeserieslabels":["dump_event"]},"id":"oVDxnV72FY","from_name":"phase","to_name":"ts","type":"timeserieslabels","origin":"manual"},{"value":{"start":"2025-07-31T22:32:14.829000","end":"2025-07-31T22:38:12.248000","instant":false,"timeserieslabels":["load_event"]},"id":"vhl7E3yv-P","from_name":"phase","to_name":"ts","type":"timeserieslabels","origin":"manual"},{"value":{"start":"2025-07-31T23:01:46.889000","end":"2025-07-31T23:03:03.973000","instant":false,"timeserieslabels":["dump_event"]},"id":"tF7ZOH_bQF","from_name":"phase","to_name":"ts","type":"timeserieslabels","origin":"manual"},{"value":{"start":"2025-07-31T23:17:00.472000","end":"2025-07-31T23:23:11.866000","instant":false,"timeserieslabels":["load_event"]},"id":"5lA_8bz_-d","from_name":"phase","to_name":"ts","type":"timeserieslabels","origin":"manual"},{"value":{"start":"2025-07-31T23:31:42.898000","end":"2025-07-31T23:32:59.990000","instant":false,"timeserieslabels":["dump_event"]},"id":"vMZ9EXY63I","from_name":"phase","to_name":"ts","type":"timeserieslabels","origin":"manual"},{"value":{"start":"2025-07-31T23:41:24.570000","end":"2025-07-31T23:46:39.406000","instant":false,"timeserieslabels":["load_event"]},"id":"Rg-QJ2YeJy","from_name":"phase","to_name":"ts","type":"timeserieslabels","origin":"manual"},{"value":{"start":"2025-07-31T23:55:24.970000","end":"2025-07-31T23:56:42.057000","instant":false,"timeserieslabels":["dump_event"]},"id":"3LNOBYUDFv","from_name":"phase","to_name":"ts","type":"timeserieslabels","origin":"manual"}],"was_cancelled":false,"ground_truth":false,"created_at":"2025-08-28T01:00:41.856078Z","updated_at":"2025-08-28T01:00:41.856092Z","draft_created_at":"2025-08-28T00:57:28.038901Z","lead_time":224.03,"prediction":{},"result_count":48,"unique_id":"ab545166-6e25-456b-b853-37bbe37fd504","import_id":null,"last_action":null,"bulk_created":false,"task":21,"project":14,"updated_by":1,"parent_prediction":null,"parent_annotation":null,"last_created_by":null}],"file_upload":"8951f22c-lake-605-8-0883_2025-07-31_task.json","drafts":[],"predictions":[],"data":{"truck_id":"lake-605-8-0883","date":"2025-07-31","csv_url":"\/data\/upload\/14\/178565e6-lake-605-8-0883_2025-07-31.csv"},"meta":{},"created_at":"2025-08-28T00:56:25.952360Z","updated_at":"2025-08-28T01:00:41.923162Z","inner_id":9,"total_annotations":1,"cancelled_annotations":0,"total_predictions":0,"comment_count":0,"unresolved_comment_count":0,"last_comment_updated_at":null,"project":14,"updated_by":1,"comment_authors":[]},{"id":22,"annotations":[{"id":8,"completed_by":1,"result":[{"value":{"start":"2025-08-01T12:27:47.292000","end":"2025-08-01T12:36:24.867000","instant":false,"timeserieslabels":["load_event"]},"id":"BOZ2tGYKvt","from_name":"phase","to_name":"ts","type":"timeserieslabels","origin":"manual"},{"value":{"start":"2025-08-01T12:54:44.083000","end":"2025-08-01T12:57:58.317000","instant":false,"timeserieslabels":["dump_event"]},"id":"2gQVeiZL9h","from_name":"phase","to_name":"ts","type":"timeserieslabels","origin":"manual"},{"value":{"start":"2025-08-01T13:07:19.020000","end":"2025-08-01T13:13:46.984000","instant":false,"timeserieslabels":["load_event"]},"id":"HKFqjsrTC9","from_name":"phase","to_name":"ts","type":"timeserieslabels","origin":"manual"},{"value":{"start":"2025-08-01T13:20:36.475000","end":"2025-08-01T13:29:14.093000","instant":false,"timeserieslabels":["dump_event"]},"id":"67JJ5UTlYl","from_name":"phase","to_name":"ts","type":"timeserieslabels","origin":"manual"},{"value":{"start":"2025-08-01T13:42:53.042000","end":"2025-08-01T13:50:47.620000","instant":false,"timeserieslabels":["load_event"]},"id":"QZN72_uOoH","from_name":"phase","to_name":"ts","type":"timeserieslabels","origin":"manual"},{"value":{"start":"2025-08-01T13:58:20.176000","end":"2025-08-01T14:02:17.436000","instant":false,"timeserieslabels":["dump_event"]},"id":"NUu8hAkVaK","from_name":"phase","to_name":"ts","type":"timeserieslabels","origin":"manual"},{"value":{"start":"2025-08-01T14:19:42.185000","end":"2025-08-01T14:24:44.518000","instant":false,"timeserieslabels":["load_event"]},"id":"ZHvJDRug3y","from_name":"phase","to_name":"ts","type":"timeserieslabels","origin":"manual"},{"value":{"start":"2025-08-01T14:31:47.001000","end":"2025-08-01T14:33:21.599000","instant":false,"timeserieslabels":["dump_event"]},"id":"pDiIqnFhgd","from_name":"phase","to_name":"ts","type":"timeserieslabels","origin":"manual"},{"value":{"start":"2025-08-01T14:46:17.971000","end":"2025-08-01T14:58:13.806000","instant":false,"timeserieslabels":["load_event"]},"id":"J_qN2pKpgp","from_name":"phase","to_name":"ts","type":"timeserieslabels","origin":"manual"},{"value":{"start":"2025-08-01T15:16:20.577000","end":"2025-08-01T15:17:46.679000","instant":false,"timeserieslabels":["dump_event"]},"id":"kuWgyI-VY_","from_name":"phase","to_name":"ts","type":"timeserieslabels","origin":"manual"},{"value":{"start":"2025-08-01T15:24:06.116000","end":"2025-08-01T15:31:26.132000","instant":false,"timeserieslabels":["load_event"]},"id":"NJXLRIE2kl","from_name":"phase","to_name":"ts","type":"timeserieslabels","origin":"manual"},{"value":{"start":"2025-08-01T15:47:57.306000","end":"2025-08-01T15:49:32.420000","instant":false,"timeserieslabels":["dump_event"]},"id":"Jus696AaC_","from_name":"phase","to_name":"ts","type":"timeserieslabels","origin":"manual"},{"value":{"start":"2025-08-01T15:54:34.273000","end":"2025-08-01T16:01:02.201000","instant":false,"timeserieslabels":["load_event"]},"id":"ApQUakpHwp","from_name":"phase","to_name":"ts","type":"timeserieslabels","origin":"manual"},{"value":{"start":"2025-08-01T16:11:31.962000","end":"2025-08-01T16:12:58.069000","instant":false,"timeserieslabels":["dump_event"]},"id":"o-qhB9LGeh","from_name":"phase","to_name":"ts","type":"timeserieslabels","origin":"manual"},{"value":{"start":"2025-08-01T16:17:59.953000","end":"2025-08-01T16:23:53.394000","instant":false,"timeserieslabels":["load_event"]},"id":"npYaP305fd","from_name":"phase","to_name":"ts","type":"timeserieslabels","origin":"manual"},{"value":{"start":"2025-08-01T16:40:25.531000","end":"2025-08-01T16:41:51.625000","instant":false,"timeserieslabels":["dump_event"]},"id":"rgGCcH5LoU","from_name":"phase","to_name":"ts","type":"timeserieslabels","origin":"manual"},{"value":{"start":"2025-08-01T16:47:36.524000","end":"2025-08-01T16:51:55.330000","instant":false,"timeserieslabels":["load_event"]},"id":"lO-0FebIN8","from_name":"phase","to_name":"ts","type":"timeserieslabels","origin":"manual"},{"value":{"start":"2025-08-01T17:02:16.566000","end":"2025-08-01T17:03:42.668000","instant":false,"timeserieslabels":["dump_event"]},"id":"FRdQ9ppuYf","from_name":"phase","to_name":"ts","type":"timeserieslabels","origin":"manual"},{"value":{"start":"2025-08-01T17:09:04.548000","end":"2025-08-01T17:14:06.391000","instant":false,"timeserieslabels":["load_event"]},"id":"nQSXUGfKFz","from_name":"phase","to_name":"ts","type":"timeserieslabels","origin":"manual"},{"value":{"start":"2025-08-01T17:27:28.833000","end":"2025-08-01T17:28:46.414000","instant":false,"timeserieslabels":["dump_event"]},"id":"qoqtSZQWU8","from_name":"phase","to_name":"ts","type":"timeserieslabels","origin":"manual"},{"value":{"start":"2025-08-01T17:34:39.838000","end":"2025-08-01T17:39:33.162000","instant":false,"timeserieslabels":["load_event"]},"id":"WKbbN7IXwL","from_name":"phase","to_name":"ts","type":"timeserieslabels","origin":"manual"},{"value":{"start":"2025-08-01T17:50:02.910000","end":"2025-08-01T17:51:20.499000","instant":false,"timeserieslabels":["dump_event"]},"id":"26vCPsNL6h","from_name":"phase","to_name":"ts","type":"timeserieslabels","origin":"manual"},{"value":{"start":"2025-08-01T17:57:05.407000","end":"2025-08-01T18:02:07.259000","instant":false,"timeserieslabels":["load_event"]},"id":"sUIqedv9ju","from_name":"phase","to_name":"ts","type":"timeserieslabels","origin":"manual"},{"value":{"start":"2025-08-01T18:16:03.762000","end":"2025-08-01T18:18:13.414000","instant":false,"timeserieslabels":["dump_event"]},"id":"LMNnMVyUrt","from_name":"phase","to_name":"ts","type":"timeserieslabels","origin":"manual"},{"value":{"start":"2025-08-01T19:10:58.648000","end":"2025-08-01T19:17:00.594000","instant":false,"timeserieslabels":["load_event"]},"id":"IT5vo8qqwb","from_name":"phase","to_name":"ts","type":"timeserieslabels","origin":"manual"},{"value":{"start":"2025-08-01T19:23:40.056000","end":"2025-08-01T19:24:57.645000","instant":false,"timeserieslabels":["dump_event"]},"id":"F-NhKZzMiI","from_name":"phase","to_name":"ts","type":"timeserieslabels","origin":"manual"},{"value":{"start":"2025-08-01T19:30:42.566000","end":"2025-08-01T19:35:53.407000","instant":false,"timeserieslabels":["load_event"]},"id":"4EZeCSadbS","from_name":"phase","to_name":"ts","type":"timeserieslabels","origin":"manual"},{"value":{"start":"2025-08-01T19:43:56.010000","end":"2025-08-01T19:45:22.616000","instant":false,"timeserieslabels":["dump_event"]},"id":"SlAkB4dXE-","from_name":"phase","to_name":"ts","type":"timeserieslabels","origin":"manual"},{"value":{"start":"2025-08-01T19:55:43.357000","end":"2025-08-01T20:00:19.186000","instant":false,"timeserieslabels":["load_event"]},"id":"FX1CmpnbXe","from_name":"phase","to_name":"ts","type":"timeserieslabels","origin":"manual"},{"value":{"start":"2025-08-01T20:07:39.224000","end":"2025-08-01T20:09:05.332000","instant":false,"timeserieslabels":["dump_event"]},"id":"gBIP3SjYkh","from_name":"phase","to_name":"ts","type":"timeserieslabels","origin":"manual"},{"value":{"start":"2025-08-01T20:14:50.761000","end":"2025-08-01T20:20:44.186000","instant":false,"timeserieslabels":["load_event"]},"id":"v6XFzlH2Cr","from_name":"phase","to_name":"ts","type":"timeserieslabels","origin":"manual"},{"value":{"start":"2025-08-01T20:27:46.703000","end":"2025-08-01T20:29:30.332000","instant":false,"timeserieslabels":["dump_event"]},"id":"M8RYv6uSCY","from_name":"phase","to_name":"ts","type":"timeserieslabels","origin":"manual"},{"value":{"start":"2025-08-01T20:39:18.516000","end":"2025-08-01T20:44:28.910000","instant":false,"timeserieslabels":["load_event"]},"id":"3xODzLgPna","from_name":"phase","to_name":"ts","type":"timeserieslabels","origin":"manual"},{"value":{"start":"2025-08-01T20:51:31.432000","end":"2025-08-01T20:53:06.533000","instant":false,"timeserieslabels":["dump_event"]},"id":"bENTNDwAGw","from_name":"phase","to_name":"ts","type":"timeserieslabels","origin":"manual"},{"value":{"start":"2025-08-01T20:59:08.463000","end":"2025-08-01T21:04:10.317000","instant":false,"timeserieslabels":["load_event"]},"id":"xUbd5APfoe","from_name":"phase","to_name":"ts","type":"timeserieslabels","origin":"manual"},{"value":{"start":"2025-08-01T21:10:21.312000","end":"2025-08-01T21:12:04.932000","instant":false,"timeserieslabels":["dump_event"]},"id":"Vcs9b3wtzv","from_name":"phase","to_name":"ts","type":"timeserieslabels","origin":"manual"},{"value":{"start":"2025-08-01T21:16:49.781000","end":"2025-08-01T21:24:26.806000","instant":false,"timeserieslabels":["load_event"]},"id":"1AqY9n3VBO","from_name":"phase","to_name":"ts","type":"timeserieslabels","origin":"manual"},{"value":{"start":"2025-08-01T21:33:21.461000","end":"2025-08-01T21:34:56.090000","instant":false,"timeserieslabels":["dump_event"]},"id":"SSQNMhCReO","from_name":"phase","to_name":"ts","type":"timeserieslabels","origin":"manual"},{"value":{"start":"2025-08-01T21:41:24.600000","end":"2025-08-01T21:47:26.516000","instant":false,"timeserieslabels":["load_event"]},"id":"znJg4ekkXK","from_name":"phase","to_name":"ts","type":"timeserieslabels","origin":"manual"},{"value":{"start":"2025-08-01T21:55:21.072000","end":"2025-08-01T21:57:13.208000","instant":false,"timeserieslabels":["dump_event"]},"id":"PW2I-WYgNQ","from_name":"phase","to_name":"ts","type":"timeserieslabels","origin":"manual"},{"value":{"start":"2025-08-01T22:06:24.856000","end":"2025-08-01T22:13:19.307000","instant":false,"timeserieslabels":["load_event"]},"id":"pgSHQ9foUq","from_name":"phase","to_name":"ts","type":"timeserieslabels","origin":"manual"},{"value":{"start":"2025-08-01T22:24:23.085000","end":"2025-08-01T22:25:58.199000","instant":false,"timeserieslabels":["dump_event"]},"id":"Yrnx3_8-3O","from_name":"phase","to_name":"ts","type":"timeserieslabels","origin":"manual"},{"value":{"start":"2025-08-01T22:45:39.553000","end":"2025-08-01T22:47:49.229000","instant":false,"timeserieslabels":["dump_event"]},"id":"d2SBG1UT7H","from_name":"phase","to_name":"ts","type":"timeserieslabels","origin":"manual"}],"was_cancelled":false,"ground_truth":false,"created_at":"2025-08-28T01:03:55.131211Z","updated_at":"2025-08-28T01:03:55.131225Z","draft_created_at":"2025-08-28T01:01:03.918304Z","lead_time":179.603,"prediction":{},"result_count":43,"unique_id":"bbd3ee00-395c-45f4-9eca-9f5d80d4e88b","import_id":null,"last_action":null,"bulk_created":false,"task":22,"project":14,"updated_by":1,"parent_prediction":null,"parent_annotation":null,"last_created_by":null}],"file_upload":"4d5ae879-lake-605-8-0883_2025-08-01_task.json","drafts":[],"predictions":[],"data":{"truck_id":"lake-605-8-0883","date":"2025-08-01","csv_url":"\/data\/upload\/14\/c4b38e57-lake-605-8-0883_2025-08-01.csv"},"meta":{},"created_at":"2025-08-28T00:56:25.952392Z","updated_at":"2025-08-28T01:03:55.206667Z","inner_id":10,"total_annotations":1,"cancelled_annotations":0,"total_predictions":0,"comment_count":0,"unresolved_comment_count":0,"last_comment_updated_at":null,"project":14,"updated_by":1,"comment_authors":[]},{"id":23,"annotations":[{"id":9,"completed_by":1,"result":[{"value":{"start":"2025-08-02T12:00:17.390000","end":"2025-08-02T12:08:36.484000","instant":false,"timeserieslabels":["load_event"]},"id":"1OzUweUmh-","from_name":"phase","to_name":"ts","type":"timeserieslabels","origin":"manual"},{"value":{"start":"2025-08-02T12:23:52.535000","end":"2025-08-02T12:26:35.733000","instant":false,"timeserieslabels":["dump_event"]},"id":"p4eePkkWyb","from_name":"phase","to_name":"ts","type":"timeserieslabels","origin":"manual"},{"value":{"start":"2025-08-02T12:31:00.519000","end":"2025-08-02T12:38:07.995000","instant":false,"timeserieslabels":["load_event"]},"id":"fVp0w3_iQs","from_name":"phase","to_name":"ts","type":"timeserieslabels","origin":"manual"},{"value":{"start":"2025-08-02T12:44:34.955000","end":"2025-08-02T12:46:06.561000","instant":false,"timeserieslabels":["dump_event"]},"id":"n8WfKEGRWa","from_name":"phase","to_name":"ts","type":"timeserieslabels","origin":"manual"},{"value":{"start":"2025-08-02T12:53:34.099000","end":"2025-08-02T13:00:31.582000","instant":false,"timeserieslabels":["load_event"]},"id":"6LK1f5JF-7","from_name":"phase","to_name":"ts","type":"timeserieslabels","origin":"manual"},{"value":{"start":"2025-08-02T13:05:57.449000","end":"2025-08-02T13:08:20.135000","instant":false,"timeserieslabels":["dump_event"]},"id":"h3Vw-spQbw","from_name":"phase","to_name":"ts","type":"timeserieslabels","origin":"manual"},{"value":{"start":"2025-08-02T13:15:17.620000","end":"2025-08-02T13:21:14.009000","instant":false,"timeserieslabels":["load_event"]},"id":"_9Dns-9jij","from_name":"phase","to_name":"ts","type":"timeserieslabels","origin":"manual"},{"value":{"start":"2025-08-02T13:37:31.165000","end":"2025-08-02T13:39:43.314000","instant":false,"timeserieslabels":["dump_event"]},"id":"FHskT4Wp8t","from_name":"phase","to_name":"ts","type":"timeserieslabels","origin":"manual"},{"value":{"start":"2025-08-02T13:48:02.383000","end":"2025-08-02T13:54:39.336000","instant":false,"timeserieslabels":["load_event"]},"id":"pUAMHvPubh","from_name":"phase","to_name":"ts","type":"timeserieslabels","origin":"manual"},{"value":{"start":"2025-08-02T14:10:56.974000","end":"2025-08-02T14:13:09.131000","instant":false,"timeserieslabels":["dump_event"]},"id":"KJiZtnXyfN","from_name":"phase","to_name":"ts","type":"timeserieslabels","origin":"manual"},{"value":{"start":"2025-08-02T14:19:46.094000","end":"2025-08-02T14:27:04.090000","instant":false,"timeserieslabels":["load_event"]},"id":"Ar3sttHk92","from_name":"phase","to_name":"ts","type":"timeserieslabels","origin":"manual"},{"value":{"start":"2025-08-02T14:34:20.590000","end":"2025-08-02T14:36:12.234000","instant":false,"timeserieslabels":["dump_event"]},"id":"rV6kS_zUzL","from_name":"phase","to_name":"ts","type":"timeserieslabels","origin":"manual"},{"value":{"start":"2025-08-02T14:40:47.047000","end":"2025-08-02T14:47:34.524000","instant":false,"timeserieslabels":["load_event"]},"id":"RJNkv8ZvDH","from_name":"phase","to_name":"ts","type":"timeserieslabels","origin":"manual"},{"value":{"start":"2025-08-02T14:58:46.302000","end":"2025-08-02T15:00:58.954000","instant":false,"timeserieslabels":["dump_event"]},"id":"eDf_YgAUTD","from_name":"phase","to_name":"ts","type":"timeserieslabels","origin":"manual"},{"value":{"start":"2025-08-02T15:08:26.459000","end":"2025-08-02T15:16:04.964000","instant":false,"timeserieslabels":["load_event"]},"id":"jTkHbu24II","from_name":"phase","to_name":"ts","type":"timeserieslabels","origin":"manual"},{"value":{"start":"2025-08-02T15:25:35.151000","end":"2025-08-02T15:27:26.776000","instant":false,"timeserieslabels":["dump_event"]},"id":"ACrKY_7en5","from_name":"phase","to_name":"ts","type":"timeserieslabels","origin":"manual"},{"value":{"start":"2025-08-02T15:37:47.977000","end":"2025-08-02T15:44:55.466000","instant":false,"timeserieslabels":["load_event"]},"id":"ONGPkklKpR","from_name":"phase","to_name":"ts","type":"timeserieslabels","origin":"manual"},{"value":{"start":"2025-08-02T15:52:54.016000","end":"2025-08-02T15:54:56.158000","instant":false,"timeserieslabels":["dump_event"]},"id":"TWJtJSqu6u","from_name":"phase","to_name":"ts","type":"timeserieslabels","origin":"manual"},{"value":{"start":"2025-08-02T16:04:46.822000","end":"2025-08-02T16:12:34.833000","instant":false,"timeserieslabels":["load_event"]},"id":"ZjGBZv34f8","from_name":"phase","to_name":"ts","type":"timeserieslabels","origin":"manual"},{"value":{"start":"2025-08-02T16:22:04.987000","end":"2025-08-02T16:24:37.662000","instant":false,"timeserieslabels":["dump_event"]},"id":"hkIfJWOCYf","from_name":"phase","to_name":"ts","type":"timeserieslabels","origin":"manual"},{"value":{"start":"2025-08-02T16:31:15.116000","end":"2025-08-02T16:39:03.135000","instant":false,"timeserieslabels":["load_event"]},"id":"AcTrhngsQj","from_name":"phase","to_name":"ts","type":"timeserieslabels","origin":"manual"},{"value":{"start":"2025-08-02T16:50:55.931000","end":"2025-08-02T16:53:28.618000","instant":false,"timeserieslabels":["dump_event"]},"id":"6PQJM49rnv","from_name":"phase","to_name":"ts","type":"timeserieslabels","origin":"manual"},{"value":{"start":"2025-08-02T17:00:32.114000","end":"2025-08-02T17:08:00.144000","instant":false,"timeserieslabels":["load_event"]},"id":"hKGvzwiaSU","from_name":"phase","to_name":"ts","type":"timeserieslabels","origin":"manual"},{"value":{"start":"2025-08-02T17:16:39.261000","end":"2025-08-02T17:18:10.867000","instant":false,"timeserieslabels":["dump_event"]},"id":"S85jKmx1Ck","from_name":"phase","to_name":"ts","type":"timeserieslabels","origin":"manual"},{"value":{"start":"2025-08-02T17:26:49.976000","end":"2025-08-02T17:33:16.918000","instant":false,"timeserieslabels":["load_event"]},"id":"oO1s88-br5","from_name":"phase","to_name":"ts","type":"timeserieslabels","origin":"manual"},{"value":{"start":"2025-08-02T17:46:20.871000","end":"2025-08-02T17:48:43.540000","instant":false,"timeserieslabels":["dump_event"]},"id":"fOK2HHxuk7","from_name":"phase","to_name":"ts","type":"timeserieslabels","origin":"manual"},{"value":{"start":"2025-08-02T17:53:18.362000","end":"2025-08-02T18:00:56.408000","instant":false,"timeserieslabels":["load_event"]},"id":"pgB884vCAG","from_name":"phase","to_name":"ts","type":"timeserieslabels","origin":"manual"},{"value":{"start":"2025-08-02T18:13:50.308000","end":"2025-08-02T18:16:02.473000","instant":false,"timeserieslabels":["dump_event"]},"id":"OS7op9_zNR","from_name":"phase","to_name":"ts","type":"timeserieslabels","origin":"manual"},{"value":{"start":"2025-08-02T18:25:12.113000","end":"2025-08-02T18:32:20.102000","instant":false,"timeserieslabels":["load_event"]},"id":"pBiOLrtnvN","from_name":"phase","to_name":"ts","type":"timeserieslabels","origin":"manual"},{"value":{"start":"2025-08-02T18:41:29.783000","end":"2025-08-02T18:43:01.389000","instant":false,"timeserieslabels":["dump_event"]},"id":"jSSIGlA5U8","from_name":"phase","to_name":"ts","type":"timeserieslabels","origin":"manual"},{"value":{"start":"2025-08-02T18:52:21.117000","end":"2025-08-02T18:57:36.993000","instant":false,"timeserieslabels":["load_event"]},"id":"tHpzOUYf4A","from_name":"phase","to_name":"ts","type":"timeserieslabels","origin":"manual"},{"value":{"start":"2025-08-02T19:10:10.353000","end":"2025-08-02T19:11:51.971000","instant":false,"timeserieslabels":["dump_event"]},"id":"DbCXRE9zbT","from_name":"phase","to_name":"ts","type":"timeserieslabels","origin":"manual"},{"value":{"start":"2025-08-02T19:19:56.519000","end":"2025-08-02T19:26:33.488000","instant":false,"timeserieslabels":["load_event"]},"id":"rEOUVi1iuW","from_name":"phase","to_name":"ts","type":"timeserieslabels","origin":"manual"},{"value":{"start":"2025-08-02T19:33:31.015000","end":"2025-08-02T19:35:33.162000","instant":false,"timeserieslabels":["dump_event"]},"id":"Rs_WmykOnq","from_name":"phase","to_name":"ts","type":"timeserieslabels","origin":"manual"},{"value":{"start":"2025-08-02T19:41:39.640000","end":"2025-08-02T19:48:47.176000","instant":false,"timeserieslabels":["load_event"]},"id":"70SG7Ppzgx","from_name":"phase","to_name":"ts","type":"timeserieslabels","origin":"manual"},{"value":{"start":"2025-08-02T19:56:45.793000","end":"2025-08-02T19:59:18.471000","instant":false,"timeserieslabels":["dump_event"]},"id":"IVJHzwvPl7","from_name":"phase","to_name":"ts","type":"timeserieslabels","origin":"manual"},{"value":{"start":"2025-08-02T20:06:56.541000","end":"2025-08-02T20:13:33.499000","instant":false,"timeserieslabels":["load_event"]},"id":"5eyyrXBU9Q","from_name":"phase","to_name":"ts","type":"timeserieslabels","origin":"manual"},{"value":{"start":"2025-08-02T20:20:00.460000","end":"2025-08-02T20:22:53.661000","instant":false,"timeserieslabels":["dump_event"]},"id":"Q0ZQGDSqQp","from_name":"phase","to_name":"ts","type":"timeserieslabels","origin":"manual"},{"value":{"start":"2025-08-02T20:31:02.255000","end":"2025-08-02T20:37:59.752000","instant":false,"timeserieslabels":["load_event"]},"id":"v9kaoGbUFl","from_name":"phase","to_name":"ts","type":"timeserieslabels","origin":"manual"},{"value":{"start":"2025-08-02T20:44:57.270000","end":"2025-08-02T20:46:38.878000","instant":false,"timeserieslabels":["dump_event"]},"id":"PP4ThWFlBk","from_name":"phase","to_name":"ts","type":"timeserieslabels","origin":"manual"},{"value":{"start":"2025-08-02T20:51:54.257000","end":"2025-08-02T20:59:52.806000","instant":false,"timeserieslabels":["load_event"]},"id":"g65iVFDsB_","from_name":"phase","to_name":"ts","type":"timeserieslabels","origin":"manual"},{"value":{"start":"2025-08-02T21:07:41.370000","end":"2025-08-02T21:09:43.515000","instant":false,"timeserieslabels":["dump_event"]},"id":"IaMz7Cf-WJ","from_name":"phase","to_name":"ts","type":"timeserieslabels","origin":"manual"},{"value":{"start":"2025-08-02T21:14:10.838000","end":"2025-08-02T21:21:59.368000","instant":false,"timeserieslabels":["load_event"]},"id":"uf7bMa8yk6","from_name":"phase","to_name":"ts","type":"timeserieslabels","origin":"manual"},{"value":{"start":"2025-08-02T21:29:37.413000","end":"2025-08-02T21:31:19.040000","instant":false,"timeserieslabels":["dump_event"]},"id":"GHiHPEI6ax","from_name":"phase","to_name":"ts","type":"timeserieslabels","origin":"manual"},{"value":{"start":"2025-08-02T21:37:56.039000","end":"2025-08-02T21:45:04.021000","instant":false,"timeserieslabels":["load_event"]},"id":"JsUQL-ph15","from_name":"phase","to_name":"ts","type":"timeserieslabels","origin":"manual"},{"value":{"start":"2025-08-02T21:52:31.547000","end":"2025-08-02T21:54:34.188000","instant":false,"timeserieslabels":["dump_event"]},"id":"qWpYz-X-_Y","from_name":"phase","to_name":"ts","type":"timeserieslabels","origin":"manual"},{"value":{"start":"2025-08-02T22:03:33.308000","end":"2025-08-02T22:10:00.293000","instant":false,"timeserieslabels":["load_event"]},"id":"vX008MRyA6","from_name":"phase","to_name":"ts","type":"timeserieslabels","origin":"manual"},{"value":{"start":"2025-08-02T22:16:06.730000","end":"2025-08-02T22:18:59.910000","instant":false,"timeserieslabels":["dump_event"]},"id":"Jd9pD9TKxl","from_name":"phase","to_name":"ts","type":"timeserieslabels","origin":"manual"},{"value":{"start":"2025-08-02T22:26:48.487000","end":"2025-08-02T22:37:09.222000","instant":false,"timeserieslabels":["load_event"]},"id":"ugRWgknR6T","from_name":"phase","to_name":"ts","type":"timeserieslabels","origin":"manual"},{"value":{"start":"2025-08-02T22:45:28.316000","end":"2025-08-02T22:47:30.446000","instant":false,"timeserieslabels":["dump_event"]},"id":"pTKVO2D8Ok","from_name":"phase","to_name":"ts","type":"timeserieslabels","origin":"manual"}],"was_cancelled":false,"ground_truth":false,"created_at":"2025-08-28T01:06:42.968603Z","updated_at":"2025-08-28T01:06:42.968617Z","draft_created_at":"2025-08-28T01:04:16.857513Z","lead_time":165.51,"prediction":{},"result_count":50,"unique_id":"c5bf6372-2252-430a-a5f4-c8302ef89c21","import_id":null,"last_action":null,"bulk_created":false,"task":23,"project":14,"updated_by":1,"parent_prediction":null,"parent_annotation":null,"last_created_by":null}],"file_upload":"dbffcf4e-lake-605-8-0883_2025-08-02_task.json","drafts":[],"predictions":[],"data":{"truck_id":"lake-605-8-0883","date":"2025-08-02","csv_url":"\/data\/upload\/14\/e2c69bbb-lake-605-8-0883_2025-08-02.csv"},"meta":{},"created_at":"2025-08-28T00:56:25.952422Z","updated_at":"2025-08-28T01:06:43.070134Z","inner_id":11,"total_annotations":1,"cancelled_annotations":0,"total_predictions":0,"comment_count":0,"unresolved_comment_count":0,"last_comment_updated_at":null,"project":14,"updated_by":1,"comment_authors":[]},{"id":24,"annotations":[{"id":10,"completed_by":1,"result":[{"value":{"start":"2025-08-03T12:28:53.320000","end":"2025-08-03T12:32:36.102000","instant":false,"timeserieslabels":["load_event"]},"id":"ZE0E9_LFiV","from_name":"phase","to_name":"ts","type":"timeserieslabels","origin":"manual"},{"value":{"start":"2025-08-03T12:44:43.502000","end":"2025-08-03T12:46:30.114000","instant":false,"timeserieslabels":["dump_event"]},"id":"bc7wQVwvNa","from_name":"phase","to_name":"ts","type":"timeserieslabels","origin":"manual"},{"value":{"start":"2025-08-03T12:51:30.467000","end":"2025-08-03T12:55:13.738000","instant":false,"timeserieslabels":["load_event"]},"id":"6wXHHU4rQl","from_name":"phase","to_name":"ts","type":"timeserieslabels","origin":"manual"},{"value":{"start":"2025-08-03T13:01:12.164000","end":"2025-08-03T13:03:37.825000","instant":false,"timeserieslabels":["dump_event"]},"id":"o8Ck7Ajj9E","from_name":"phase","to_name":"ts","type":"timeserieslabels","origin":"manual"},{"value":{"start":"2025-08-03T13:11:32.425000","end":"2025-08-03T13:16:23.266000","instant":false,"timeserieslabels":["load_event"]},"id":"W9j31pxfJJ","from_name":"phase","to_name":"ts","type":"timeserieslabels","origin":"manual"},{"value":{"start":"2025-08-03T13:31:05.799000","end":"2025-08-03T13:33:50.509000","instant":false,"timeserieslabels":["dump_event"]},"id":"lb70z-j50m","from_name":"phase","to_name":"ts","type":"timeserieslabels","origin":"manual"},{"value":{"start":"2025-08-03T13:44:11.186000","end":"2025-08-03T13:51:46.690000","instant":false,"timeserieslabels":["load_event"]},"id":"KStx5SURWo","from_name":"phase","to_name":"ts","type":"timeserieslabels","origin":"manual"},{"value":{"start":"2025-08-03T13:57:34.647000","end":"2025-08-03T14:00:38.861000","instant":false,"timeserieslabels":["dump_event"]},"id":"6uBy-TuxEP","from_name":"phase","to_name":"ts","type":"timeserieslabels","origin":"manual"},{"value":{"start":"2025-08-03T14:09:51.475000","end":"2025-08-03T14:14:32.815000","instant":false,"timeserieslabels":["load_event"]},"id":"yUlWjovOKD","from_name":"phase","to_name":"ts","type":"timeserieslabels","origin":"manual"},{"value":{"start":"2025-08-03T14:21:00.786000","end":"2025-08-03T14:22:47.404000","instant":false,"timeserieslabels":["dump_event"]},"id":"QQe9RsQzVd","from_name":"phase","to_name":"ts","type":"timeserieslabels","origin":"manual"},{"value":{"start":"2025-08-03T14:33:46.703000","end":"2025-08-03T14:38:18.014000","instant":false,"timeserieslabels":["load_event"]},"id":"_ptS_pXAFj","from_name":"phase","to_name":"ts","type":"timeserieslabels","origin":"manual"},{"value":{"start":"2025-08-03T14:44:06.930000","end":"2025-08-03T14:45:44.035000","instant":false,"timeserieslabels":["dump_event"]},"id":"x40GsNlspJ","from_name":"phase","to_name":"ts","type":"timeserieslabels","origin":"manual"},{"value":{"start":"2025-08-03T14:57:02.321000","end":"2025-08-03T15:01:43.621000","instant":false,"timeserieslabels":["load_event"]},"id":"A-6OzP_R2x","from_name":"phase","to_name":"ts","type":"timeserieslabels","origin":"manual"},{"value":{"start":"2025-08-03T15:12:03.880000","end":"2025-08-03T15:13:40.994000","instant":false,"timeserieslabels":["dump_event"]},"id":"DuFSfKkGGP","from_name":"phase","to_name":"ts","type":"timeserieslabels","origin":"manual"},{"value":{"start":"2025-08-03T15:23:03.155000","end":"2025-08-03T15:28:42.567000","instant":false,"timeserieslabels":["load_event"]},"id":"Z9hsdUnvlv","from_name":"phase","to_name":"ts","type":"timeserieslabels","origin":"manual"},{"value":{"start":"2025-08-03T15:34:21.953000","end":"2025-08-03T15:35:49.051000","instant":false,"timeserieslabels":["dump_event"]},"id":"1lFg7ado3N","from_name":"phase","to_name":"ts","type":"timeserieslabels","origin":"manual"},{"value":{"start":"2025-08-03T15:47:46.837000","end":"2025-08-03T15:52:08.639000","instant":false,"timeserieslabels":["load_event"]},"id":"JFhQWTGey_","from_name":"phase","to_name":"ts","type":"timeserieslabels","origin":"manual"},{"value":{"start":"2025-08-03T16:08:17.725000","end":"2025-08-03T16:10:33.385000","instant":false,"timeserieslabels":["dump_event"]},"id":"NBBpNb4bBT","from_name":"phase","to_name":"ts","type":"timeserieslabels","origin":"manual"},{"value":{"start":"2025-08-03T16:16:51.849000","end":"2025-08-03T16:25:15.895000","instant":false,"timeserieslabels":["load_event"]},"id":"gJ2QmCXCYJ","from_name":"phase","to_name":"ts","type":"timeserieslabels","origin":"manual"},{"value":{"start":"2025-08-03T16:32:51.431000","end":"2025-08-03T16:36:15.179000","instant":false,"timeserieslabels":["dump_event"]},"id":"_0b5NZbnKv","from_name":"phase","to_name":"ts","type":"timeserieslabels","origin":"manual"},{"value":{"start":"2025-08-03T16:45:23.796000","end":"2025-08-03T16:54:26.920000","instant":false,"timeserieslabels":["load_event"]},"id":"I707dovSN1","from_name":"phase","to_name":"ts","type":"timeserieslabels","origin":"manual"},{"value":{"start":"2025-08-03T16:58:48.704000","end":"2025-08-03T17:00:25.316000","instant":false,"timeserieslabels":["dump_event"]},"id":"MFDB9z8v8Q","from_name":"phase","to_name":"ts","type":"timeserieslabels","origin":"manual"},{"value":{"start":"2025-08-03T17:17:42.972000","end":"2025-08-03T17:25:08.975000","instant":false,"timeserieslabels":["load_event"]},"id":"dB4N1itr_p","from_name":"phase","to_name":"ts","type":"timeserieslabels","origin":"manual"},{"value":{"start":"2025-08-03T17:37:25.832000","end":"2025-08-03T17:39:12.447000","instant":false,"timeserieslabels":["dump_event"]},"id":"ZP1UXkr6-h","from_name":"phase","to_name":"ts","type":"timeserieslabels","origin":"manual"},{"value":{"start":"2025-08-03T17:50:30.690000","end":"2025-08-03T17:56:29.610000","instant":false,"timeserieslabels":["load_event"]},"id":"KAPodhslDM","from_name":"phase","to_name":"ts","type":"timeserieslabels","origin":"manual"},{"value":{"start":"2025-08-03T18:01:00.925000","end":"2025-08-03T18:02:57.551000","instant":false,"timeserieslabels":["dump_event"]},"id":"cGcLhIrSeN","from_name":"phase","to_name":"ts","type":"timeserieslabels","origin":"manual"},{"value":{"start":"2025-08-03T18:17:39.557000","end":"2025-08-03T18:25:44.139000","instant":false,"timeserieslabels":["load_event"]},"id":"ZvVHciBNxh","from_name":"phase","to_name":"ts","type":"timeserieslabels","origin":"manual"},{"value":{"start":"2025-08-03T18:34:08.753000","end":"2025-08-03T18:36:14.394000","instant":false,"timeserieslabels":["dump_event"]},"id":"4yxGHBgFIg","from_name":"phase","to_name":"ts","type":"timeserieslabels","origin":"manual"},{"value":{"start":"2025-08-03T18:50:11.354000","end":"2025-08-03T18:57:47.360000","instant":false,"timeserieslabels":["load_event"]},"id":"EfK3bYT3PV","from_name":"phase","to_name":"ts","type":"timeserieslabels","origin":"manual"},{"value":{"start":"2025-08-03T19:06:20.953000","end":"2025-08-03T19:08:27.111000","instant":false,"timeserieslabels":["dump_event"]},"id":"8WC1NU9qe7","from_name":"phase","to_name":"ts","type":"timeserieslabels","origin":"manual"},{"value":{"start":"2025-08-03T19:21:03.460000","end":"2025-08-03T19:28:38.984000","instant":false,"timeserieslabels":["load_event"]},"id":"xlUJDTGB6U","from_name":"phase","to_name":"ts","type":"timeserieslabels","origin":"manual"},{"value":{"start":"2025-08-03T19:37:12.584000","end":"2025-08-03T19:39:28.237000","instant":false,"timeserieslabels":["dump_event"]},"id":"8EJc9zGaEH","from_name":"phase","to_name":"ts","type":"timeserieslabels","origin":"manual"},{"value":{"start":"2025-08-03T19:47:04.242000","end":"2025-08-03T19:50:57.018000","instant":false,"timeserieslabels":["load_event"]},"id":"j_MDl-0ht-","from_name":"phase","to_name":"ts","type":"timeserieslabels","origin":"manual"},{"value":{"start":"2025-08-03T19:57:44.028000","end":"2025-08-03T20:00:28.714000","instant":false,"timeserieslabels":["dump_event"]},"id":"94l9Hj5AjH","from_name":"phase","to_name":"ts","type":"timeserieslabels","origin":"manual"},{"value":{"start":"2025-08-03T20:08:43.284000","end":"2025-08-03T20:13:53.623000","instant":false,"timeserieslabels":["load_event"]},"id":"goM9ZLkZQy","from_name":"phase","to_name":"ts","type":"timeserieslabels","origin":"manual"},{"value":{"start":"2025-08-03T20:19:13.473000","end":"2025-08-03T20:20:50.106000","instant":false,"timeserieslabels":["dump_event"]},"id":"4dJsGDYAdF","from_name":"phase","to_name":"ts","type":"timeserieslabels","origin":"manual"},{"value":{"start":"2025-08-03T20:29:14.706000","end":"2025-08-03T20:34:15.070000","instant":false,"timeserieslabels":["load_event"]},"id":"OMEF6Ul9Et","from_name":"phase","to_name":"ts","type":"timeserieslabels","origin":"manual"},{"value":{"start":"2025-08-03T20:40:43.044000","end":"2025-08-03T20:42:48.686000","instant":false,"timeserieslabels":["dump_event"]},"id":"FcuRiGqllO","from_name":"phase","to_name":"ts","type":"timeserieslabels","origin":"manual"},{"value":{"start":"2025-08-03T20:51:33.294000","end":"2025-08-03T21:00:35.913000","instant":false,"timeserieslabels":["load_event"]},"id":"3CK8LoyVcM","from_name":"phase","to_name":"ts","type":"timeserieslabels","origin":"manual"},{"value":{"start":"2025-08-03T21:08:01.949000","end":"2025-08-03T21:09:58.077000","instant":false,"timeserieslabels":["dump_event"]},"id":"VrhA0OibuO","from_name":"phase","to_name":"ts","type":"timeserieslabels","origin":"manual"},{"value":{"start":"2025-08-03T21:17:24.092000","end":"2025-08-03T21:24:11.518000","instant":false,"timeserieslabels":["load_event"]},"id":"nGkQn0AJaZ","from_name":"phase","to_name":"ts","type":"timeserieslabels","origin":"manual"},{"value":{"start":"2025-08-03T21:30:29.470000","end":"2025-08-03T21:32:25.612000","instant":false,"timeserieslabels":["dump_event"]},"id":"H0jCyZ6Qr4","from_name":"phase","to_name":"ts","type":"timeserieslabels","origin":"manual"}],"was_cancelled":false,"ground_truth":false,"created_at":"2025-08-28T01:08:45.430951Z","updated_at":"2025-08-28T01:08:45.430965Z","draft_created_at":"2025-08-28T01:06:53.438910Z","lead_time":120.78,"prediction":{},"result_count":42,"unique_id":"b2c08c62-1d89-4056-b687-5c2b0391659a","import_id":null,"last_action":null,"bulk_created":false,"task":24,"project":14,"updated_by":1,"parent_prediction":null,"parent_annotation":null,"last_created_by":null}],"file_upload":"8b14f708-lake-605-8-0883_2025-08-03_task.json","drafts":[],"predictions":[],"data":{"truck_id":"lake-605-8-0883","date":"2025-08-03","csv_url":"\/data\/upload\/14\/ef552224-lake-605-8-0883_2025-08-03.csv"},"meta":{},"created_at":"2025-08-28T00:56:25.952450Z","updated_at":"2025-08-28T01:08:45.503545Z","inner_id":12,"total_annotations":1,"cancelled_annotations":0,"total_predictions":0,"comment_count":0,"unresolved_comment_count":0,"last_comment_updated_at":null,"project":14,"updated_by":1,"comment_authors":[]},{"id":26,"annotations":[{"id":11,"completed_by":1,"result":[{"value":{"start":"2025-08-05T12:35:32.555000","end":"2025-08-05T12:46:52.824000","instant":false,"timeserieslabels":["load_event"]},"id":"AL_5m1hRDu","from_name":"phase","to_name":"ts","type":"timeserieslabels","origin":"manual"},{"value":{"start":"2025-08-05T12:55:56.940000","end":"2025-08-05T12:59:13.178000","instant":false,"timeserieslabels":["dump_event"]},"id":"zRo20iBQHk","from_name":"phase","to_name":"ts","type":"timeserieslabels","origin":"manual"},{"value":{"start":"2025-08-05T13:02:59.950000","end":"2025-08-05T13:07:47.279000","instant":false,"timeserieslabels":["load_event"]},"id":"saU6nRJwYy","from_name":"phase","to_name":"ts","type":"timeserieslabels","origin":"manual"},{"value":{"start":"2025-08-05T13:13:34.667000","end":"2025-08-05T13:16:35.879000","instant":false,"timeserieslabels":["dump_event"]},"id":"HtlRswLMZ5","from_name":"phase","to_name":"ts","type":"timeserieslabels","origin":"manual"},{"value":{"start":"2025-08-05T13:21:23.212000","end":"2025-08-05T13:29:41.775000","instant":false,"timeserieslabels":["load_event"]},"id":"tNmKc526o3","from_name":"phase","to_name":"ts","type":"timeserieslabels","origin":"manual"},{"value":{"start":"2025-08-05T13:34:59.167000","end":"2025-08-05T13:37:30.348000","instant":false,"timeserieslabels":["dump_event"]},"id":"-KixnaT4gy","from_name":"phase","to_name":"ts","type":"timeserieslabels","origin":"manual"},{"value":{"start":"2025-08-05T13:43:48.292000","end":"2025-08-05T13:53:22.471000","instant":false,"timeserieslabels":["load_event"]},"id":"N8ThWppEEB","from_name":"phase","to_name":"ts","type":"timeserieslabels","origin":"manual"},{"value":{"start":"2025-08-05T14:07:58.991000","end":"2025-08-05T14:13:01.326000","instant":false,"timeserieslabels":["dump_event"]},"id":"ecI4rWXzVh","from_name":"phase","to_name":"ts","type":"timeserieslabels","origin":"manual"},{"value":{"start":"2025-08-05T14:18:34.175000","end":"2025-08-05T14:26:07.196000","instant":false,"timeserieslabels":["load_event"]},"id":"yy96i2UmnC","from_name":"phase","to_name":"ts","type":"timeserieslabels","origin":"manual"},{"value":{"start":"2025-08-05T14:30:08.987000","end":"2025-08-05T14:33:55.756000","instant":false,"timeserieslabels":["dump_event"]},"id":"seXRH5z1Xx","from_name":"phase","to_name":"ts","type":"timeserieslabels","origin":"manual"},{"value":{"start":"2025-08-05T14:37:42.536000","end":"2025-08-05T14:42:14.408000","instant":false,"timeserieslabels":["load_event"]},"id":"evf3uUcK56","from_name":"phase","to_name":"ts","type":"timeserieslabels","origin":"manual"},{"value":{"start":"2025-08-05T14:46:31.687000","end":"2025-08-05T14:51:34.043000","instant":false,"timeserieslabels":["dump_event"]},"id":"r2x1sWf5qN","from_name":"phase","to_name":"ts","type":"timeserieslabels","origin":"manual"},{"value":{"start":"2025-08-05T14:54:50.268000","end":"2025-08-05T15:00:07.630000","instant":false,"timeserieslabels":["load_event"]},"id":"KqEvI_Ayvo","from_name":"phase","to_name":"ts","type":"timeserieslabels","origin":"manual"},{"value":{"start":"2025-08-05T15:47:28.970000","end":"2025-08-05T15:52:01.280000","instant":false,"timeserieslabels":["dump_event"]},"id":"tNVsDa2PSh","from_name":"phase","to_name":"ts","type":"timeserieslabels","origin":"manual"},{"value":{"start":"2025-08-05T15:58:03.724000","end":"2025-08-05T16:06:37.813000","instant":false,"timeserieslabels":["load_event"]},"id":"nEAzIWP9_O","from_name":"phase","to_name":"ts","type":"timeserieslabels","origin":"manual"},{"value":{"start":"2025-08-05T16:13:25.770000","end":"2025-08-05T16:16:41.994000","instant":false,"timeserieslabels":["dump_event"]},"id":"8ByW09lNhY","from_name":"phase","to_name":"ts","type":"timeserieslabels","origin":"manual"},{"value":{"start":"2025-08-05T16:21:29.352000","end":"2025-08-05T16:30:33.504000","instant":false,"timeserieslabels":["load_event"]},"id":"EQmW8ixXFA","from_name":"phase","to_name":"ts","type":"timeserieslabels","origin":"manual"},{"value":{"start":"2025-08-05T16:37:26.453000","end":"2025-08-05T16:40:12.654000","instant":false,"timeserieslabels":["dump_event"]},"id":"H74m6bqPfx","from_name":"phase","to_name":"ts","type":"timeserieslabels","origin":"manual"},{"value":{"start":"2025-08-05T16:47:15.669000","end":"2025-08-05T16:53:03.583000","instant":false,"timeserieslabels":["load_event"]},"id":"no_h_KFVYF","from_name":"phase","to_name":"ts","type":"timeserieslabels","origin":"manual"},{"value":{"start":"2025-08-05T17:10:41.292000","end":"2025-08-05T17:13:12.459000","instant":false,"timeserieslabels":["dump_event"]},"id":"OPjTF1IMnH","from_name":"phase","to_name":"ts","type":"timeserieslabels","origin":"manual"},{"value":{"start":"2025-08-05T17:23:17.204000","end":"2025-08-05T17:28:49.584000","instant":false,"timeserieslabels":["load_event"]},"id":"YQO_fNOGKT","from_name":"phase","to_name":"ts","type":"timeserieslabels","origin":"manual"},{"value":{"start":"2025-08-05T17:37:53.727000","end":"2025-08-05T17:41:55.546000","instant":false,"timeserieslabels":["dump_event"]},"id":"SLuZDMvNul","from_name":"phase","to_name":"ts","type":"timeserieslabels","origin":"manual"},{"value":{"start":"2025-08-05T17:45:57.332000","end":"2025-08-05T17:50:29.146000","instant":false,"timeserieslabels":["load_event"]},"id":"pCPUEbFQcN","from_name":"phase","to_name":"ts","type":"timeserieslabels","origin":"manual"},{"value":{"start":"2025-08-05T17:55:31.503000","end":"2025-08-05T17:59:18.262000","instant":false,"timeserieslabels":["dump_event"]},"id":"a1Ova1wJrD","from_name":"phase","to_name":"ts","type":"timeserieslabels","origin":"manual"},{"value":{"start":"2025-08-05T18:06:06.232000","end":"2025-08-05T18:12:24.179000","instant":false,"timeserieslabels":["load_event"]},"id":"aUgTMUI1xD","from_name":"phase","to_name":"ts","type":"timeserieslabels","origin":"manual"},{"value":{"start":"2025-08-05T18:19:42.205000","end":"2025-08-05T18:22:58.925000","instant":false,"timeserieslabels":["dump_event"]},"id":"XR0koKGnOB","from_name":"phase","to_name":"ts","type":"timeserieslabels","origin":"manual"},{"value":{"start":"2025-08-05T18:33:48.719000","end":"2025-08-05T18:41:22.232000","instant":false,"timeserieslabels":["load_event"]},"id":"jBuCfK6o8b","from_name":"phase","to_name":"ts","type":"timeserieslabels","origin":"manual"},{"value":{"start":"2025-08-05T18:46:54.646000","end":"2025-08-05T18:49:55.865000","instant":false,"timeserieslabels":["dump_event"]},"id":"rgDs4ZX5JD","from_name":"phase","to_name":"ts","type":"timeserieslabels","origin":"manual"},{"value":{"start":"2025-08-05T19:02:46.719000","end":"2025-08-05T19:09:34.758000","instant":false,"timeserieslabels":["load_event"]},"id":"b8KoiJvjVb","from_name":"phase","to_name":"ts","type":"timeserieslabels","origin":"manual"},{"value":{"start":"2025-08-05T19:21:55.619000","end":"2025-08-05T19:24:41.808000","instant":false,"timeserieslabels":["dump_event"]},"id":"Pu1FOrwvcu","from_name":"phase","to_name":"ts","type":"timeserieslabels","origin":"manual"},{"value":{"start":"2025-08-05T19:44:35.678000","end":"2025-08-05T19:48:37.453000","instant":false,"timeserieslabels":["load_event"]},"id":"01x9jZMS1h","from_name":"phase","to_name":"ts","type":"timeserieslabels","origin":"manual"},{"value":{"start":"2025-08-05T19:57:41.610000","end":"2025-08-05T20:01:13.357000","instant":false,"timeserieslabels":["dump_event"]},"id":"nuKVJhrfvw","from_name":"phase","to_name":"ts","type":"timeserieslabels","origin":"manual"},{"value":{"start":"2025-08-05T20:08:31.378000","end":"2025-08-05T20:13:48.735000","instant":false,"timeserieslabels":["load_event"]},"id":"XCmVzfYky1","from_name":"phase","to_name":"ts","type":"timeserieslabels","origin":"manual"},{"value":{"start":"2025-08-05T20:21:37.297000","end":"2025-08-05T20:24:23.479000","instant":false,"timeserieslabels":["dump_event"]},"id":"iUVPFAab5A","from_name":"phase","to_name":"ts","type":"timeserieslabels","origin":"manual"},{"value":{"start":"2025-08-05T20:30:26.429000","end":"2025-08-05T20:35:13.246000","instant":false,"timeserieslabels":["load_event"]},"id":"h1tB-I64sG","from_name":"phase","to_name":"ts","type":"timeserieslabels","origin":"manual"},{"value":{"start":"2025-08-05T20:52:51.511000","end":"2025-08-05T20:56:07.747000","instant":false,"timeserieslabels":["dump_event"]},"id":"hvqbIxJAb8","from_name":"phase","to_name":"ts","type":"timeserieslabels","origin":"manual"},{"value":{"start":"2025-08-05T21:06:12.420000","end":"2025-08-05T21:11:29.797000","instant":false,"timeserieslabels":["load_event"]},"id":"jbcBEAAmrj","from_name":"phase","to_name":"ts","type":"timeserieslabels","origin":"manual"},{"value":{"start":"2025-08-05T21:27:08.848000","end":"2025-08-05T21:29:39.524000","instant":false,"timeserieslabels":["dump_event"]},"id":"9MvL2_H7ML","from_name":"phase","to_name":"ts","type":"timeserieslabels","origin":"manual"},{"value":{"start":"2025-08-05T21:39:29.207000","end":"2025-08-05T21:46:17.194000","instant":false,"timeserieslabels":["load_event"]},"id":"orCwmWhCfp","from_name":"phase","to_name":"ts","type":"timeserieslabels","origin":"manual"},{"value":{"start":"2025-08-05T21:52:20.133000","end":"2025-08-05T21:56:06.413000","instant":false,"timeserieslabels":["dump_event"]},"id":"mC7l_2w0m2","from_name":"phase","to_name":"ts","type":"timeserieslabels","origin":"manual"},{"value":{"start":"2025-08-05T22:00:53.750000","end":"2025-08-05T22:08:27.270000","instant":false,"timeserieslabels":["load_event"]},"id":"mgbGOhelRP","from_name":"phase","to_name":"ts","type":"timeserieslabels","origin":"manual"},{"value":{"start":"2025-08-05T22:17:31.432000","end":"2025-08-05T22:20:17.610000","instant":false,"timeserieslabels":["dump_event"]},"id":"mP1o6wMe1g","from_name":"phase","to_name":"ts","type":"timeserieslabels","origin":"manual"},{"value":{"start":"2025-08-05T22:26:35.536000","end":"2025-08-05T22:35:24.153000","instant":false,"timeserieslabels":["load_event"]},"id":"3ReZf0dZi7","from_name":"phase","to_name":"ts","type":"timeserieslabels","origin":"manual"},{"value":{"start":"2025-08-05T22:42:27.637000","end":"2025-08-05T22:45:58.875000","instant":false,"timeserieslabels":["dump_event"]},"id":"RMS6PLcRrl","from_name":"phase","to_name":"ts","type":"timeserieslabels","origin":"manual"}],"was_cancelled":false,"ground_truth":false,"created_at":"2025-08-28T01:11:17.115078Z","updated_at":"2025-08-28T01:11:17.115093Z","draft_created_at":"2025-08-28T01:09:12.692044Z","lead_time":142.084,"prediction":{},"result_count":44,"unique_id":"e8d50caa-ccd1-417f-9aa7-ec9f772404b9","import_id":null,"last_action":null,"bulk_created":false,"task":26,"project":14,"updated_by":1,"parent_prediction":null,"parent_annotation":null,"last_created_by":null}],"file_upload":"c558c52d-lake-605-8-0883_2025-08-05_task.json","drafts":[],"predictions":[],"data":{"truck_id":"lake-605-8-0883","date":"2025-08-05","csv_url":"\/data\/upload\/14\/6e3a952d-lake-605-8-0883_2025-08-05.csv"},"meta":{},"created_at":"2025-08-28T00:56:25.952506Z","updated_at":"2025-08-28T01:11:17.198569Z","inner_id":14,"total_annotations":1,"cancelled_annotations":0,"total_predictions":0,"comment_count":0,"unresolved_comment_count":0,"last_comment_updated_at":null,"project":14,"updated_by":1,"comment_authors":[]}]