[{"id":2,"annotations":[{"id":1,"completed_by":1,"result":[{"value":{"start":"2025-08-01T12:37:47.535000","end":"2025-08-01T12:44:30.472000","instant":false,"timeserieslabels":["load_event"]},"id":"J-iu0UoWnX","from_name":"phase","to_name":"ts","type":"timeserieslabels","origin":"manual"},{"value":{"start":"2025-08-01T13:12:54.389000","end":"2025-08-01T13:19:03.802000","instant":false,"timeserieslabels":["load_event"]},"id":"KXN9dqKAv2","from_name":"phase","to_name":"ts","type":"timeserieslabels","origin":"manual"},{"value":{"start":"2025-08-01T13:49:17.365000","end":"2025-08-01T13:56:16.856000","instant":false,"timeserieslabels":["load_event"]},"id":"-DYzXIqG1L","from_name":"phase","to_name":"ts","type":"timeserieslabels","origin":"manual"},{"value":{"start":"2025-08-01T14:25:31.433000","end":"2025-08-01T14:31:23.841000","instant":false,"timeserieslabels":["load_event"]},"id":"a09PNEfF7x","from_name":"phase","to_name":"ts","type":"timeserieslabels","origin":"manual"},{"value":{"start":"2025-08-01T12:57:47.849000","end":"2025-08-01T13:00:02.003000","instant":false,"timeserieslabels":["dump_event"]},"id":"CEK7EdKrDA","from_name":"phase","to_name":"ts","type":"timeserieslabels","origin":"manual"},{"value":{"start":"2025-08-01T13:28:42.951000","end":"2025-08-01T13:30:07.038000","instant":false,"timeserieslabels":["dump_event"]},"id":"RQm-2L5FFQ","from_name":"phase","to_name":"ts","type":"timeserieslabels","origin":"manual"},{"value":{"start":"2025-08-01T14:02:34.774000","end":"2025-08-01T14:03:50.369000","instant":false,"timeserieslabels":["dump_event"]},"id":"XbJNUwOcit","from_name":"phase","to_name":"ts","type":"timeserieslabels","origin":"manual"},{"value":{"start":"2025-08-01T14:38:23.840000","end":"2025-08-01T14:39:30.910000","instant":false,"timeserieslabels":["dump_event"]},"id":"BYD4tJkaL8","from_name":"phase","to_name":"ts","type":"timeserieslabels","origin":"manual"},{"value":{"start":"2025-08-01T15:18:13.019000","end":"2025-08-01T15:24:22.457000","instant":false,"timeserieslabels":["load_event"]},"id":"YmuUreez3k","from_name":"phase","to_name":"ts","type":"timeserieslabels","origin":"manual"},{"value":{"start":"2025-08-01T15:38:38.929000","end":"2025-08-01T15:44:47.854000","instant":false,"timeserieslabels":["load_event"]},"id":"9P0347U3ic","from_name":"phase","to_name":"ts","type":"timeserieslabels","origin":"manual"},{"value":{"start":"2025-08-01T16:00:36.438000","end":"2025-08-01T16:06:12.314000","instant":false,"timeserieslabels":["load_event"]},"id":"VopyQW2S8T","from_name":"phase","to_name":"ts","type":"timeserieslabels","origin":"manual"},{"value":{"start":"2025-08-01T16:24:32.120000","end":"2025-08-01T16:29:50.984000","instant":false,"timeserieslabels":["load_event"]},"id":"Sz1kWmMJdw","from_name":"phase","to_name":"ts","type":"timeserieslabels","origin":"manual"},{"value":{"start":"2025-08-01T16:51:48.978000","end":"2025-08-01T16:57:24.860000","instant":false,"timeserieslabels":["load_event"]},"id":"Hsj8KwFt53","from_name":"phase","to_name":"ts","type":"timeserieslabels","origin":"manual"},{"value":{"start":"2025-08-01T15:31:55.974000","end":"2025-08-01T15:32:54.539000","instant":false,"timeserieslabels":["dump_event"]},"id":"1vWH9KMaMg","from_name":"phase","to_name":"ts","type":"timeserieslabels","origin":"manual"},{"value":{"start":"2025-08-01T15:52:29.888000","end":"2025-08-01T15:53:36.956000","instant":false,"timeserieslabels":["dump_event"]},"id":"wcU_4nmAkE","from_name":"phase","to_name":"ts","type":"timeserieslabels","origin":"manual"},{"value":{"start":"2025-08-01T16:13:54.377000","end":"2025-08-01T16:15:09.968000","instant":false,"timeserieslabels":["dump_event"]},"id":"hXwJykPYNy","from_name":"phase","to_name":"ts","type":"timeserieslabels","origin":"manual"},{"value":{"start":"2025-08-01T16:42:51.840000","end":"2025-08-01T16:44:07.433000","instant":false,"timeserieslabels":["dump_event"]},"id":"_gEomd88ES","from_name":"phase","to_name":"ts","type":"timeserieslabels","origin":"manual"},{"value":{"start":"2025-08-01T17:07:54.593000","end":"2025-08-01T17:09:18.700000","instant":false,"timeserieslabels":["dump_event"]},"id":"2GtDL56NKm","from_name":"phase","to_name":"ts","type":"timeserieslabels","origin":"manual"},{"value":{"start":"2025-08-01T17:14:21.054000","end":"2025-08-01T17:19:23.400000","instant":false,"timeserieslabels":["load_event"]},"id":"ukVuv6Rjel","from_name":"phase","to_name":"ts","type":"timeserieslabels","origin":"manual"},{"value":{"start":"2025-08-01T17:33:05.845000","end":"2025-08-01T17:34:12.921000","instant":false,"timeserieslabels":["dump_event"]},"id":"PzzkZdZoZK","from_name":"phase","to_name":"ts","type":"timeserieslabels","origin":"manual"},{"value":{"start":"2025-08-01T17:39:57.318000","end":"2025-08-01T17:44:42.652000","instant":false,"timeserieslabels":["load_event"]},"id":"Q6PXZFptnM","from_name":"phase","to_name":"ts","type":"timeserieslabels","origin":"manual"},{"value":{"start":"2025-08-01T17:51:42.657000","end":"2025-08-01T17:52:57.744000","instant":false,"timeserieslabels":["dump_event"]},"id":"uiqVcjCuuA","from_name":"phase","to_name":"ts","type":"timeserieslabels","origin":"manual"},{"value":{"start":"2025-08-01T18:02:11.892000","end":"2025-08-01T18:06:49.196000","instant":false,"timeserieslabels":["load_event"]},"id":"rJydsu-dlx","from_name":"phase","to_name":"ts","type":"timeserieslabels","origin":"manual"},{"value":{"start":"2025-08-01T18:18:42.564000","end":"2025-08-01T18:20:06.656000","instant":false,"timeserieslabels":["dump_event"]},"id":"hc-vaAM2dC","from_name":"phase","to_name":"ts","type":"timeserieslabels","origin":"manual"},{"value":{"start":"2025-08-01T19:17:30.513000","end":"2025-08-01T19:23:14.888000","instant":false,"timeserieslabels":["load_event"]},"id":"SXIIuQ-cS1","from_name":"phase","to_name":"ts","type":"timeserieslabels","origin":"manual"},{"value":{"start":"2025-08-01T19:30:31.400000","end":"2025-08-01T19:31:29.972000","instant":false,"timeserieslabels":["dump_event"]},"id":"IHqqxpY5Ke","from_name":"phase","to_name":"ts","type":"timeserieslabels","origin":"manual"},{"value":{"start":"2025-08-01T19:40:44.079000","end":"2025-08-01T19:46:44.989000","instant":false,"timeserieslabels":["load_event"]},"id":"_OhAyNOBS8","from_name":"phase","to_name":"ts","type":"timeserieslabels","origin":"manual"},{"value":{"start":"2025-08-01T19:56:16.144000","end":"2025-08-01T19:57:23.218000","instant":false,"timeserieslabels":["dump_event"]},"id":"cjES2EU4kO","from_name":"phase","to_name":"ts","type":"timeserieslabels","origin":"manual"},{"value":{"start":"2025-08-01T20:05:04.767000","end":"2025-08-01T20:10:57.664000","instant":false,"timeserieslabels":["load_event"]},"id":"LNU7xfW8LZ","from_name":"phase","to_name":"ts","type":"timeserieslabels","origin":"manual"},{"value":{"start":"2025-08-01T20:18:39.218000","end":"2025-08-01T20:19:21.260000","instant":false,"timeserieslabels":["dump_event"]},"id":"uNnd5IA-LD","from_name":"phase","to_name":"ts","type":"timeserieslabels","origin":"manual"},{"value":{"start":"2025-08-01T20:26:03.750000","end":"2025-08-01T20:32:13.170000","instant":false,"timeserieslabels":["load_event"]},"id":"1BbLKE7pwi","from_name":"phase","to_name":"ts","type":"timeserieslabels","origin":"manual"},{"value":{"start":"2025-08-01T20:39:21.658000","end":"2025-08-01T20:40:28.763000","instant":false,"timeserieslabels":["dump_event"]},"id":"pIkW-OVHyH","from_name":"phase","to_name":"ts","type":"timeserieslabels","origin":"manual"},{"value":{"start":"2025-08-01T20:49:34.405000","end":"2025-08-01T20:55:35.310000","instant":false,"timeserieslabels":["load_event"]},"id":"cjwauBp1AW","from_name":"phase","to_name":"ts","type":"timeserieslabels","origin":"manual"},{"value":{"start":"2025-08-01T21:02:34.781000","end":"2025-08-01T21:03:50.359000","instant":false,"timeserieslabels":["dump_event"]},"id":"UZtV14InDv","from_name":"phase","to_name":"ts","type":"timeserieslabels","origin":"manual"},{"value":{"start":"2025-08-01T21:10:25.289000","end":"2025-08-01T21:18:06.816000","instant":false,"timeserieslabels":["load_event"]},"id":"0vWiXZzJAa","from_name":"phase","to_name":"ts","type":"timeserieslabels","origin":"manual"},{"value":{"start":"2025-08-01T21:23:51.217000","end":"2025-08-01T21:25:06.805000","instant":false,"timeserieslabels":["dump_event"]},"id":"utBmC9rwLe","from_name":"phase","to_name":"ts","type":"timeserieslabels","origin":"manual"},{"value":{"start":"2025-08-01T21:32:39.807000","end":"2025-08-01T21:38:32.705000","instant":false,"timeserieslabels":["load_event"]},"id":"_u63G62lkz","from_name":"phase","to_name":"ts","type":"timeserieslabels","origin":"manual"},{"value":{"start":"2025-08-01T21:45:57.216000","end":"2025-08-01T21:47:29.827000","instant":false,"timeserieslabels":["dump_event"]},"id":"1JmLrKWp7s","from_name":"phase","to_name":"ts","type":"timeserieslabels","origin":"manual"},{"value":{"start":"2025-08-01T22:01:05.282000","end":"2025-08-01T22:07:23.240000","instant":false,"timeserieslabels":["load_event"]},"id":"tQYBHSUIg6","from_name":"phase","to_name":"ts","type":"timeserieslabels","origin":"manual"},{"value":{"start":"2025-08-01T22:13:15.666000","end":"2025-08-01T22:14:14.225000","instant":false,"timeserieslabels":["dump_event"]},"id":"0Fe51zIrch","from_name":"phase","to_name":"ts","type":"timeserieslabels","origin":"manual"},{"value":{"start":"2025-08-01T22:20:23.650000","end":"2025-08-01T22:25:42.535000","instant":false,"timeserieslabels":["load_event"]},"id":"a62cNhU_hl","from_name":"phase","to_name":"ts","type":"timeserieslabels","origin":"manual"},{"value":{"start":"2025-08-01T22:32:17.505000","end":"2025-08-01T22:33:33.093000","instant":false,"timeserieslabels":["dump_event"]},"id":"Pxf2BzkdT_","from_name":"phase","to_name":"ts","type":"timeserieslabels","origin":"manual"},{"value":{"start":"2025-08-01T22:40:57.594000","end":"2025-08-01T22:46:33.465000","instant":false,"timeserieslabels":["load_event"]},"id":"E2MQNoU5Lw","from_name":"phase","to_name":"ts","type":"timeserieslabels","origin":"manual"},{"value":{"start":"2025-08-01T22:59:00.807000","end":"2025-08-01T23:00:24.412000","instant":false,"timeserieslabels":["dump_event"]},"id":"hUh-ljwqlt","from_name":"phase","to_name":"ts","type":"timeserieslabels","origin":"manual"}],"was_cancelled":false,"ground_truth":false,"created_at":"2025-08-28T00:15:58.722419Z","updated_at":"2025-08-28T00:15:58.722436Z","draft_created_at":"2025-08-28T00:12:52.979363Z","lead_time":292.382,"prediction":{},"result_count":44,"unique_id":"4a3c086d-0a48-457a-b5f1-40cf7212a7ac","import_id":null,"last_action":null,"bulk_created":false,"task":2,"project":13,"updated_by":1,"parent_prediction":null,"parent_annotation":null,"last_created_by":null}],"file_upload":"6652c41b-lake-605-10-0050_2025-08-01_task.json","drafts":[],"predictions":[],"data":{"truck_id":"lake-605-10-0050","date":"2025-08-01","csv_url":"\/data\/upload\/13\/0e442bbc-lake-605-10-0050_2025-08-01.csv"},"meta":{},"created_at":"2025-08-28T00:06:13.064678Z","updated_at":"2025-08-28T00:15:58.787151Z","inner_id":2,"total_annotations":1,"cancelled_annotations":0,"total_predictions":0,"comment_count":0,"unresolved_comment_count":0,"last_comment_updated_at":null,"project":13,"updated_by":1,"comment_authors":[]},{"id":3,"annotations":[{"id":2,"completed_by":1,"result":[{"value":{"start":"2025-07-30T12:33:35.812000","end":"2025-07-30T12:38:42.660000","instant":false,"timeserieslabels":["load_event"]},"id":"ljesaZdqey","from_name":"phase","to_name":"ts","type":"timeserieslabels","origin":"manual"},{"value":{"start":"2025-07-30T12:45:20.620000","end":"2025-07-30T12:46:51.235000","instant":false,"timeserieslabels":["dump_event"]},"id":"v4YW2xLD3z","from_name":"phase","to_name":"ts","type":"timeserieslabels","origin":"manual"},{"value":{"start":"2025-07-30T12:56:53.406000","end":"2025-07-30T13:01:03.692000","instant":false,"timeserieslabels":["load_event"]},"id":"9JV18AJT-o","from_name":"phase","to_name":"ts","type":"timeserieslabels","origin":"manual"},{"value":{"start":"2025-07-30T13:16:12.746000","end":"2025-07-30T13:17:54.878000","instant":false,"timeserieslabels":["dump_event"]},"id":"Z_RSlrsEXS","from_name":"phase","to_name":"ts","type":"timeserieslabels","origin":"manual"},{"value":{"start":"2025-07-30T13:26:37.498000","end":"2025-07-30T13:31:10.286000","instant":false,"timeserieslabels":["load_event"]},"id":"O7WukaQtHt","from_name":"phase","to_name":"ts","type":"timeserieslabels","origin":"manual"},{"value":{"start":"2025-07-30T13:42:54.636000","end":"2025-07-30T13:44:14.221000","instant":false,"timeserieslabels":["dump_event"]},"id":"690hy1Q27Y","from_name":"phase","to_name":"ts","type":"timeserieslabels","origin":"manual"},{"value":{"start":"2025-07-30T13:53:42.370000","end":"2025-07-30T13:58:38.204000","instant":false,"timeserieslabels":["load_event"]},"id":"jSOFyeGjhU","from_name":"phase","to_name":"ts","type":"timeserieslabels","origin":"manual"},{"value":{"start":"2025-07-30T14:09:36.989000","end":"2025-07-30T14:11:19.120000","instant":false,"timeserieslabels":["dump_event"]},"id":"1846TxOCQD","from_name":"phase","to_name":"ts","type":"timeserieslabels","origin":"manual"},{"value":{"start":"2025-07-30T14:17:11.557000","end":"2025-07-30T14:21:10.310000","instant":false,"timeserieslabels":["load_event"]},"id":"kbs0oXEcy-","from_name":"phase","to_name":"ts","type":"timeserieslabels","origin":"manual"},{"value":{"start":"2025-07-30T14:28:33.326000","end":"2025-07-30T14:30:03.925000","instant":false,"timeserieslabels":["dump_event"]},"id":"p8TUSvpsx4","from_name":"phase","to_name":"ts","type":"timeserieslabels","origin":"manual"},{"value":{"start":"2025-07-30T14:37:49.971000","end":"2025-07-30T14:42:34.310000","instant":false,"timeserieslabels":["load_event"]},"id":"4OYXy5Ewwt","from_name":"phase","to_name":"ts","type":"timeserieslabels","origin":"manual"},{"value":{"start":"2025-07-30T14:48:37.756000","end":"2025-07-30T14:52:04.003000","instant":false,"timeserieslabels":["dump_event"]},"id":"c_tyIEbzdx","from_name":"phase","to_name":"ts","type":"timeserieslabels","origin":"manual"},{"value":{"start":"2025-07-30T15:00:20.105000","end":"2025-07-30T15:06:52.555000","instant":false,"timeserieslabels":["load_event"]},"id":"MnStzVbGyf","from_name":"phase","to_name":"ts","type":"timeserieslabels","origin":"manual"},{"value":{"start":"2025-07-30T15:19:16.412000","end":"2025-07-30T15:22:22.607000","instant":false,"timeserieslabels":["dump_event"]},"id":"ksOAEeP5gG","from_name":"phase","to_name":"ts","type":"timeserieslabels","origin":"manual"},{"value":{"start":"2025-07-30T15:30:38.183000","end":"2025-07-30T15:35:27.525000","instant":false,"timeserieslabels":["load_event"]},"id":"MMBmepiXGq","from_name":"phase","to_name":"ts","type":"timeserieslabels","origin":"manual"},{"value":{"start":"2025-07-30T15:41:59.991000","end":"2025-07-30T15:44:45.687000","instant":false,"timeserieslabels":["dump_event"]},"id":"KljAvqodjX","from_name":"phase","to_name":"ts","type":"timeserieslabels","origin":"manual"},{"value":{"start":"2025-07-30T15:51:38.640000","end":"2025-07-30T15:57:09.493000","instant":false,"timeserieslabels":["load_event"]},"id":"rhBOrcc9CY","from_name":"phase","to_name":"ts","type":"timeserieslabels","origin":"manual"},{"value":{"start":"2025-07-30T16:03:21.447000","end":"2025-07-30T16:06:27.175000","instant":false,"timeserieslabels":["dump_event"]},"id":"953fJjgQiB","from_name":"phase","to_name":"ts","type":"timeserieslabels","origin":"manual"},{"value":{"start":"2025-07-30T16:22:58.873000","end":"2025-07-30T16:28:29.757000","instant":false,"timeserieslabels":["load_event"]},"id":"o6ZcA-Izhw","from_name":"phase","to_name":"ts","type":"timeserieslabels","origin":"manual"},{"value":{"start":"2025-07-30T16:41:14.126000","end":"2025-07-30T16:44:20.355000","instant":false,"timeserieslabels":["dump_event"]},"id":"ekdRDv3Gvy","from_name":"phase","to_name":"ts","type":"timeserieslabels","origin":"manual"},{"value":{"start":"2025-07-30T16:49:30.229000","end":"2025-07-30T16:55:00.614000","instant":false,"timeserieslabels":["load_event"]},"id":"6U8z1zxEJ9","from_name":"phase","to_name":"ts","type":"timeserieslabels","origin":"manual"},{"value":{"start":"2025-07-30T17:09:49.182000","end":"2025-07-30T17:13:56.980000","instant":false,"timeserieslabels":["load_event"]},"id":"9YX0aWMDmV","from_name":"phase","to_name":"ts","type":"timeserieslabels","origin":"manual"},{"value":{"start":"2025-07-30T17:24:58.321000","end":"2025-07-30T17:27:22.987000","instant":false,"timeserieslabels":["dump_event"]},"id":"tXqJ0V06qv","from_name":"phase","to_name":"ts","type":"timeserieslabels","origin":"manual"},{"value":{"start":"2025-07-30T17:36:09.106000","end":"2025-07-30T17:40:59.436000","instant":false,"timeserieslabels":["load_event"]},"id":"hrrq5zPM4g","from_name":"phase","to_name":"ts","type":"timeserieslabels","origin":"manual"},{"value":{"start":"2025-07-30T17:48:08.461000","end":"2025-07-30T17:50:27.126000","instant":false,"timeserieslabels":["dump_event"]},"id":"onejvkeI-w","from_name":"phase","to_name":"ts","type":"timeserieslabels","origin":"manual"},{"value":{"start":"2025-07-30T18:04:03.588000","end":"2025-07-30T18:09:49.486000","instant":false,"timeserieslabels":["load_event"]},"id":"6HOIMciZj_","from_name":"phase","to_name":"ts","type":"timeserieslabels","origin":"manual"},{"value":{"start":"2025-07-30T18:25:30.569000","end":"2025-07-30T18:27:07.679000","instant":false,"timeserieslabels":["dump_event"]},"id":"coQ-Md3G8H","from_name":"phase","to_name":"ts","type":"timeserieslabels","origin":"manual"},{"value":{"start":"2025-07-30T18:32:12.050000","end":"2025-07-30T18:39:21.029000","instant":false,"timeserieslabels":["load_event"]},"id":"vPZfBMcNrw","from_name":"phase","to_name":"ts","type":"timeserieslabels","origin":"manual"},{"value":{"start":"2025-07-30T18:46:44.051000","end":"2025-07-30T18:48:34.682000","instant":false,"timeserieslabels":["dump_event"]},"id":"UVnr8M8fIL","from_name":"phase","to_name":"ts","type":"timeserieslabels","origin":"manual"},{"value":{"start":"2025-07-30T18:54:06.610000","end":"2025-07-30T19:00:21.021000","instant":false,"timeserieslabels":["load_event"]},"id":"LWHxcnEwB3","from_name":"phase","to_name":"ts","type":"timeserieslabels","origin":"manual"},{"value":{"start":"2025-07-30T19:10:42.224000","end":"2025-07-30T19:12:04.322000","instant":false,"timeserieslabels":["dump_event"]},"id":"J5bpjchALS","from_name":"phase","to_name":"ts","type":"timeserieslabels","origin":"manual"},{"value":{"start":"2025-07-30T19:18:19.274000","end":"2025-07-30T19:25:28.255000","instant":false,"timeserieslabels":["load_event"]},"id":"_qsEZtjWX0","from_name":"phase","to_name":"ts","type":"timeserieslabels","origin":"manual"},{"value":{"start":"2025-07-30T19:31:33.713000","end":"2025-07-30T19:32:55.815000","instant":false,"timeserieslabels":["dump_event"]},"id":"1q9PHo5MhZ","from_name":"phase","to_name":"ts","type":"timeserieslabels","origin":"manual"},{"value":{"start":"2025-07-30T19:40:41.856000","end":"2025-07-30T19:46:56.293000","instant":false,"timeserieslabels":["load_event"]},"id":"ZdDjafq3SS","from_name":"phase","to_name":"ts","type":"timeserieslabels","origin":"manual"},{"value":{"start":"2025-07-30T19:53:29.265000","end":"2025-07-30T19:55:00.363000","instant":false,"timeserieslabels":["dump_event"]},"id":"0ZWzwJmUQc","from_name":"phase","to_name":"ts","type":"timeserieslabels","origin":"manual"},{"value":{"start":"2025-07-30T20:02:19.892000","end":"2025-07-30T20:09:01.847000","instant":false,"timeserieslabels":["load_event"]},"id":"gwourTf8Sf","from_name":"phase","to_name":"ts","type":"timeserieslabels","origin":"manual"},{"value":{"start":"2025-07-30T20:16:02.337000","end":"2025-07-30T20:17:33.437000","instant":false,"timeserieslabels":["dump_event"]},"id":"JorcE2S9cV","from_name":"phase","to_name":"ts","type":"timeserieslabels","origin":"manual"},{"value":{"start":"2025-07-30T20:23:11.811000","end":"2025-07-30T20:29:26.263000","instant":false,"timeserieslabels":["load_event"]},"id":"-ivGyHmmvl","from_name":"phase","to_name":"ts","type":"timeserieslabels","origin":"manual"},{"value":{"start":"2025-07-30T20:35:58.715000","end":"2025-07-30T20:37:39.335000","instant":false,"timeserieslabels":["dump_event"]},"id":"s9LFm7D_sU","from_name":"phase","to_name":"ts","type":"timeserieslabels","origin":"manual"},{"value":{"start":"2025-07-30T20:47:51.540000","end":"2025-07-30T20:55:37.571000","instant":false,"timeserieslabels":["load_event"]},"id":"JdMqThm7fn","from_name":"phase","to_name":"ts","type":"timeserieslabels","origin":"manual"},{"value":{"start":"2025-07-30T21:01:05.990000","end":"2025-07-30T21:03:14.153000","instant":false,"timeserieslabels":["dump_event"]},"id":"6H2i_PMxHk","from_name":"phase","to_name":"ts","type":"timeserieslabels","origin":"manual"},{"value":{"start":"2025-07-30T21:09:19.567000","end":"2025-07-30T21:16:38.084000","instant":false,"timeserieslabels":["load_event"]},"id":"UsWWwXNIPn","from_name":"phase","to_name":"ts","type":"timeserieslabels","origin":"manual"},{"value":{"start":"2025-07-30T21:26:31.760000","end":"2025-07-30T21:28:39.897000","instant":false,"timeserieslabels":["dump_event"]},"id":"K4B8hFpD1E","from_name":"phase","to_name":"ts","type":"timeserieslabels","origin":"manual"},{"value":{"start":"2025-07-30T21:36:52.991000","end":"2025-07-30T21:43:52.969000","instant":false,"timeserieslabels":["load_event"]},"id":"VKYT-uEPsq","from_name":"phase","to_name":"ts","type":"timeserieslabels","origin":"manual"},{"value":{"start":"2025-07-30T21:54:41.707000","end":"2025-07-30T21:56:22.329000","instant":false,"timeserieslabels":["dump_event"]},"id":"4Okb7Oi2Dc","from_name":"phase","to_name":"ts","type":"timeserieslabels","origin":"manual"},{"value":{"start":"2025-07-30T22:04:17.377000","end":"2025-07-30T22:09:55.258000","instant":false,"timeserieslabels":["load_event"]},"id":"rzsNT7JXnw","from_name":"phase","to_name":"ts","type":"timeserieslabels","origin":"manual"},{"value":{"start":"2025-07-30T22:23:19.222000","end":"2025-07-30T22:25:36.374000","instant":false,"timeserieslabels":["dump_event"]},"id":"7WA3doyHvW","from_name":"phase","to_name":"ts","type":"timeserieslabels","origin":"manual"},{"value":{"start":"2025-07-30T22:34:12.975000","end":"2025-07-30T22:40:45.915000","instant":false,"timeserieslabels":["load_event"]},"id":"QOhXqrBqAs","from_name":"phase","to_name":"ts","type":"timeserieslabels","origin":"manual"},{"value":{"start":"2025-07-30T22:46:42.345000","end":"2025-07-30T22:48:13.437000","instant":false,"timeserieslabels":["dump_event"]},"id":"MTxnuA0qwv","from_name":"phase","to_name":"ts","type":"timeserieslabels","origin":"manual"},{"value":{"start":"2025-07-30T17:00:54.536000","end":"2025-07-30T17:02:16.628000","instant":false,"timeserieslabels":["dump_event"]},"id":"W6IjM3fPpe","from_name":"phase","to_name":"ts","type":"timeserieslabels","origin":"manual"}],"was_cancelled":false,"ground_truth":false,"created_at":"2025-08-28T00:27:07.708764Z","updated_at":"2025-08-28T00:27:07.708780Z","draft_created_at":"2025-08-28T00:23:14.126345Z","lead_time":292.136,"prediction":{},"result_count":50,"unique_id":"d438b188-db98-4335-ba60-cc568c813e59","import_id":null,"last_action":null,"bulk_created":false,"task":3,"project":13,"updated_by":1,"parent_prediction":null,"parent_annotation":null,"last_created_by":null}],"file_upload":"8255be59-lake-605-10-0050_2025-07-30_task.json","drafts":[],"predictions":[],"data":{"truck_id":"lake-605-10-0050","date":"2025-07-30","csv_url":"\/data\/upload\/13\/d2c555fe-lake-605-10-0050_2025-07-30.csv"},"meta":{},"created_at":"2025-08-28T00:22:14.011774Z","updated_at":"2025-08-28T00:27:07.761869Z","inner_id":3,"total_annotations":1,"cancelled_annotations":0,"total_predictions":0,"comment_count":0,"unresolved_comment_count":0,"last_comment_updated_at":null,"project":13,"updated_by":1,"comment_authors":[]},{"id":4,"annotations":[{"id":3,"completed_by":1,"result":[{"value":{"start":"2025-07-31T12:30:34.036000","end":"2025-07-31T12:35:19.851000","instant":false,"timeserieslabels":["load_event"]},"id":"JCc56dMjQs","from_name":"phase","to_name":"ts","type":"timeserieslabels","origin":"manual"},{"value":{"start":"2025-07-31T12:47:45.206000","end":"2025-07-31T12:48:56.788000","instant":false,"timeserieslabels":["dump_event"]},"id":"HIFtN-G9HA","from_name":"phase","to_name":"ts","type":"timeserieslabels","origin":"manual"},{"value":{"start":"2025-07-31T13:00:21.044000","end":"2025-07-31T13:07:40.054000","instant":false,"timeserieslabels":["load_event"]},"id":"hhwDq62yst","from_name":"phase","to_name":"ts","type":"timeserieslabels","origin":"manual"},{"value":{"start":"2025-07-31T13:19:04.349000","end":"2025-07-31T13:21:06.985000","instant":false,"timeserieslabels":["dump_event"]},"id":"MwEdAlANoF","from_name":"phase","to_name":"ts","type":"timeserieslabels","origin":"manual"},{"value":{"start":"2025-07-31T13:25:32.289000","end":"2025-07-31T13:31:50.195000","instant":false,"timeserieslabels":["load_event"]},"id":"V4RU-Pttd7","from_name":"phase","to_name":"ts","type":"timeserieslabels","origin":"manual"},{"value":{"start":"2025-07-31T13:41:11.855000","end":"2025-07-31T13:42:23.440000","instant":false,"timeserieslabels":["dump_event"]},"id":"tCPA9EO379","from_name":"phase","to_name":"ts","type":"timeserieslabels","origin":"manual"},{"value":{"start":"2025-07-31T13:52:46.171000","end":"2025-07-31T13:57:01.466000","instant":false,"timeserieslabels":["load_event"]},"id":"rNU9IncfqZ","from_name":"phase","to_name":"ts","type":"timeserieslabels","origin":"manual"},{"value":{"start":"2025-07-31T14:13:21.578000","end":"2025-07-31T14:15:03.693000","instant":false,"timeserieslabels":["dump_event"]},"id":"hYzeGdi3k_","from_name":"phase","to_name":"ts","type":"timeserieslabels","origin":"manual"},{"value":{"start":"2025-07-31T14:19:49.513000","end":"2025-07-31T14:24:15.325000","instant":false,"timeserieslabels":["load_event"]},"id":"YSCiuyZ1GL","from_name":"phase","to_name":"ts","type":"timeserieslabels","origin":"manual"},{"value":{"start":"2025-07-31T14:31:54.889000","end":"2025-07-31T14:33:06.471000","instant":false,"timeserieslabels":["dump_event"]},"id":"6cviUcJV72","from_name":"phase","to_name":"ts","type":"timeserieslabels","origin":"manual"},{"value":{"start":"2025-07-31T15:18:48.563000","end":"2025-07-31T15:23:13.869000","instant":false,"timeserieslabels":["load_event"]},"id":"BNMbpiX2RQ","from_name":"phase","to_name":"ts","type":"timeserieslabels","origin":"manual"},{"value":{"start":"2025-07-31T15:31:03.398000","end":"2025-07-31T15:33:26.583000","instant":false,"timeserieslabels":["dump_event"]},"id":"_4sHPx-BFM","from_name":"phase","to_name":"ts","type":"timeserieslabels","origin":"manual"},{"value":{"start":"2025-07-31T15:38:12.454000","end":"2025-07-31T15:42:48.303000","instant":false,"timeserieslabels":["load_event"]},"id":"9FXRlM-5mC","from_name":"phase","to_name":"ts","type":"timeserieslabels","origin":"manual"},{"value":{"start":"2025-07-31T15:51:18.912000","end":"2025-07-31T15:53:21.050000","instant":false,"timeserieslabels":["dump_event"]},"id":"YQJY5D8L1h","from_name":"phase","to_name":"ts","type":"timeserieslabels","origin":"manual"},{"value":{"start":"2025-07-31T15:59:39.006000","end":"2025-07-31T16:04:24.826000","instant":false,"timeserieslabels":["load_event"]},"id":"mO7P8fDePS","from_name":"phase","to_name":"ts","type":"timeserieslabels","origin":"manual"},{"value":{"start":"2025-07-31T16:16:50.675000","end":"2025-07-31T16:18:32.780000","instant":false,"timeserieslabels":["dump_event"]},"id":"Bhifjq1muo","from_name":"phase","to_name":"ts","type":"timeserieslabels","origin":"manual"},{"value":{"start":"2025-07-31T16:25:10.738000","end":"2025-07-31T16:30:58.170000","instant":false,"timeserieslabels":["load_event"]},"id":"S-Z-eSlHKT","from_name":"phase","to_name":"ts","type":"timeserieslabels","origin":"manual"},{"value":{"start":"2025-07-31T16:37:26.114000","end":"2025-07-31T16:39:48.795000","instant":false,"timeserieslabels":["dump_event"]},"id":"cVdUTW9zJS","from_name":"phase","to_name":"ts","type":"timeserieslabels","origin":"manual"},{"value":{"start":"2025-07-31T16:49:10.430000","end":"2025-07-31T16:54:37.326000","instant":false,"timeserieslabels":["load_event"]},"id":"t2tr48U0gX","from_name":"phase","to_name":"ts","type":"timeserieslabels","origin":"manual"},{"value":{"start":"2025-07-31T17:09:46.360000","end":"2025-07-31T17:11:38.494000","instant":false,"timeserieslabels":["dump_event"]},"id":"g3hJltv5TH","from_name":"phase","to_name":"ts","type":"timeserieslabels","origin":"manual"},{"value":{"start":"2025-07-31T17:16:51.884000","end":"2025-07-31T17:22:39.274000","instant":false,"timeserieslabels":["load_event"]},"id":"ATNVs_A_1I","from_name":"phase","to_name":"ts","type":"timeserieslabels","origin":"manual"},{"value":{"start":"2025-07-31T17:31:40.391000","end":"2025-07-31T17:33:32.510000","instant":false,"timeserieslabels":["dump_event"]},"id":"C9XUQZNP2a","from_name":"phase","to_name":"ts","type":"timeserieslabels","origin":"manual"},{"value":{"start":"2025-07-31T17:43:04.685000","end":"2025-07-31T17:46:59.449000","instant":false,"timeserieslabels":["load_event"]},"id":"NH0T6d11DS","from_name":"phase","to_name":"ts","type":"timeserieslabels","origin":"manual"},{"value":{"start":"2025-07-31T17:54:18.468000","end":"2025-07-31T17:57:12.183000","instant":false,"timeserieslabels":["dump_event"]},"id":"QrrQSuFcAQ","from_name":"phase","to_name":"ts","type":"timeserieslabels","origin":"manual"},{"value":{"start":"2025-07-31T18:02:49.122000","end":"2025-07-31T18:07:44.978000","instant":false,"timeserieslabels":["load_event"]},"id":"JCDNn-ASq8","from_name":"phase","to_name":"ts","type":"timeserieslabels","origin":"manual"},{"value":{"start":"2025-07-31T18:14:23.433000","end":"2025-07-31T18:16:15.566000","instant":false,"timeserieslabels":["dump_event"]},"id":"9MG5Uva785","from_name":"phase","to_name":"ts","type":"timeserieslabels","origin":"manual"},{"value":{"start":"2025-07-31T18:22:33.558000","end":"2025-07-31T18:27:09.360000","instant":false,"timeserieslabels":["load_event"]},"id":"U8st39kZSS","from_name":"phase","to_name":"ts","type":"timeserieslabels","origin":"manual"},{"value":{"start":"2025-07-31T18:40:23.296000","end":"2025-07-31T18:42:02.907000","instant":false,"timeserieslabels":["dump_event"]},"id":"QEQw8_Ojko","from_name":"phase","to_name":"ts","type":"timeserieslabels","origin":"manual"},{"value":{"start":"2025-07-31T18:49:18.944000","end":"2025-07-31T18:55:21.851000","instant":false,"timeserieslabels":["load_event"]},"id":"G4610GNAak","from_name":"phase","to_name":"ts","type":"timeserieslabels","origin":"manual"},{"value":{"start":"2025-07-31T19:05:57.093000","end":"2025-07-31T19:08:40.299000","instant":false,"timeserieslabels":["dump_event"]},"id":"_bKMULRHvp","from_name":"phase","to_name":"ts","type":"timeserieslabels","origin":"manual"},{"value":{"start":"2025-07-31T19:14:52.239000","end":"2025-07-31T19:21:13.667000","instant":false,"timeserieslabels":["load_event"]},"id":"uF2C2ZWIj_","from_name":"phase","to_name":"ts","type":"timeserieslabels","origin":"manual"},{"value":{"start":"2025-07-31T19:35:53.703000","end":"2025-07-31T19:38:00.838000","instant":false,"timeserieslabels":["dump_event"]},"id":"7NdqK1H7zC","from_name":"phase","to_name":"ts","type":"timeserieslabels","origin":"manual"},{"value":{"start":"2025-07-31T19:43:00.193000","end":"2025-07-31T19:47:32.500000","instant":false,"timeserieslabels":["load_event"]},"id":"fl9yyyqQNj","from_name":"phase","to_name":"ts","type":"timeserieslabels","origin":"manual"},{"value":{"start":"2025-07-31T19:59:41.354000","end":"2025-07-31T20:02:42.566000","instant":false,"timeserieslabels":["dump_event"]},"id":"0YB-YDKToy","from_name":"phase","to_name":"ts","type":"timeserieslabels","origin":"manual"},{"value":{"start":"2025-07-31T20:07:23.897000","end":"2025-07-31T20:11:56.226000","instant":false,"timeserieslabels":["load_event"]},"id":"ba2MLuTaXn","from_name":"phase","to_name":"ts","type":"timeserieslabels","origin":"manual"},{"value":{"start":"2025-07-31T20:17:59.170000","end":"2025-07-31T20:19:20.768000","instant":false,"timeserieslabels":["dump_event"]},"id":"edbM2rBvH1","from_name":"phase","to_name":"ts","type":"timeserieslabels","origin":"manual"},{"value":{"start":"2025-07-31T20:24:47.663000","end":"2025-07-31T20:29:19.998000","instant":false,"timeserieslabels":["load_event"]},"id":"udhKDS6pgE","from_name":"phase","to_name":"ts","type":"timeserieslabels","origin":"manual"},{"value":{"start":"2025-07-31T20:38:33.647000","end":"2025-07-31T20:40:49.807000","instant":false,"timeserieslabels":["dump_event"]},"id":"vtxAw-zdLQ","from_name":"phase","to_name":"ts","type":"timeserieslabels","origin":"manual"},{"value":{"start":"2025-07-31T21:00:56.764000","end":"2025-07-31T21:08:12.292000","instant":false,"timeserieslabels":["load_event"]},"id":"v1vbqsNvv9","from_name":"phase","to_name":"ts","type":"timeserieslabels","origin":"manual"},{"value":{"start":"2025-07-31T21:13:38.690000","end":"2025-07-31T21:15:27.828000","instant":false,"timeserieslabels":["dump_event"]},"id":"kC3SiILbAW","from_name":"phase","to_name":"ts","type":"timeserieslabels","origin":"manual"},{"value":{"start":"2025-07-31T21:33:45.614000","end":"2025-07-31T21:39:58.044000","instant":false,"timeserieslabels":["load_event"]},"id":"gtwXXjP7w_","from_name":"phase","to_name":"ts","type":"timeserieslabels","origin":"manual"},{"value":{"start":"2025-07-31T22:00:40.997000","end":"2025-07-31T22:02:39.130000","instant":false,"timeserieslabels":["dump_event"]},"id":"3t4rqbYTqr","from_name":"phase","to_name":"ts","type":"timeserieslabels","origin":"manual"},{"value":{"start":"2025-07-31T22:11:12.721000","end":"2025-07-31T22:17:06.654000","instant":false,"timeserieslabels":["load_event"]},"id":"ZMQgmelAoF","from_name":"phase","to_name":"ts","type":"timeserieslabels","origin":"manual"},{"value":{"start":"2025-07-31T22:25:53.284000","end":"2025-07-31T22:27:41.901000","instant":false,"timeserieslabels":["dump_event"]},"id":"JfCptokP5k","from_name":"phase","to_name":"ts","type":"timeserieslabels","origin":"manual"},{"value":{"start":"2025-07-31T22:39:11.754000","end":"2025-07-31T22:45:33.179000","instant":false,"timeserieslabels":["load_event"]},"id":"g9a1VHj7AC","from_name":"phase","to_name":"ts","type":"timeserieslabels","origin":"manual"},{"value":{"start":"2025-07-31T23:05:03.666000","end":"2025-07-31T23:06:43.284000","instant":false,"timeserieslabels":["dump_event"]},"id":"pLOd3WDQmF","from_name":"phase","to_name":"ts","type":"timeserieslabels","origin":"manual"},{"value":{"start":"2025-07-31T23:22:45.396000","end":"2025-07-31T23:28:39.294000","instant":false,"timeserieslabels":["load_event"]},"id":"tShAFtWBCS","from_name":"phase","to_name":"ts","type":"timeserieslabels","origin":"manual"},{"value":{"start":"2025-07-31T23:34:06.175000","end":"2025-07-31T23:38:47.484000","instant":false,"timeserieslabels":["dump_event"]},"id":"6MSbb5_kmV","from_name":"phase","to_name":"ts","type":"timeserieslabels","origin":"manual"},{"value":{"start":"2025-07-31T23:46:48.509000","end":"2025-07-31T23:53:45.972000","instant":false,"timeserieslabels":["load_event"]},"id":"7HcDueME-3","from_name":"phase","to_name":"ts","type":"timeserieslabels","origin":"manual"}],"was_cancelled":false,"ground_truth":false,"created_at":"2025-08-28T00:31:47.726611Z","updated_at":"2025-08-28T00:31:47.726627Z","draft_created_at":"2025-08-28T00:27:33.702370Z","lead_time":269.899,"prediction":{},"result_count":49,"unique_id":"4b9ea97d-10cb-4cfc-9b79-9a72c4a9bf68","import_id":null,"last_action":null,"bulk_created":false,"task":4,"project":13,"updated_by":1,"parent_prediction":null,"parent_annotation":null,"last_created_by":null}],"file_upload":"949f8dca-lake-605-10-0050_2025-07-31_task.json","drafts":[],"predictions":[],"data":{"truck_id":"lake-605-10-0050","date":"2025-07-31","csv_url":"\/data\/upload\/13\/b0438544-lake-605-10-0050_2025-07-31.csv"},"meta":{},"created_at":"2025-08-28T00:22:14.011821Z","updated_at":"2025-08-28T00:31:47.782869Z","inner_id":4,"total_annotations":1,"cancelled_annotations":0,"total_predictions":0,"comment_count":0,"unresolved_comment_count":0,"last_comment_updated_at":null,"project":13,"updated_by":1,"comment_authors":[]},{"id":9,"annotations":[{"id":4,"completed_by":1,"result":[{"value":{"start":"2025-08-02T12:14:02.210000","end":"2025-08-02T12:22:52.319000","instant":false,"timeserieslabels":["load_event"]},"id":"69nYewhvZj","from_name":"phase","to_name":"ts","type":"timeserieslabels","origin":"manual"},{"value":{"start":"2025-08-02T12:37:14.819000","end":"2025-08-02T12:39:30.483000","instant":false,"timeserieslabels":["dump_event"]},"id":"Tqdak0ufeC","from_name":"phase","to_name":"ts","type":"timeserieslabels","origin":"manual"},{"value":{"start":"2025-08-02T12:46:04.961000","end":"2025-08-02T12:53:40.968000","instant":false,"timeserieslabels":["load_event"]},"id":"Y5XxPRqZ6W","from_name":"phase","to_name":"ts","type":"timeserieslabels","origin":"manual"},{"value":{"start":"2025-08-02T13:01:16.499000","end":"2025-08-02T13:02:55.124000","instant":false,"timeserieslabels":["dump_event"]},"id":"D39u8Y-9oB","from_name":"phase","to_name":"ts","type":"timeserieslabels","origin":"manual"},{"value":{"start":"2025-08-02T13:08:40.554000","end":"2025-08-02T13:16:04.060000","instant":false,"timeserieslabels":["load_event"]},"id":"5Apt1n-03Y","from_name":"phase","to_name":"ts","type":"timeserieslabels","origin":"manual"},{"value":{"start":"2025-08-02T13:34:33.322000","end":"2025-08-02T13:37:25.524000","instant":false,"timeserieslabels":["dump_event"]},"id":"9hrrYFyRCF","from_name":"phase","to_name":"ts","type":"timeserieslabels","origin":"manual"},{"value":{"start":"2025-08-02T13:41:56.841000","end":"2025-08-02T13:48:43.312000","instant":false,"timeserieslabels":["load_event"]},"id":"LSrn4EeBNT","from_name":"phase","to_name":"ts","type":"timeserieslabels","origin":"manual"},{"value":{"start":"2025-08-02T13:54:16.228000","end":"2025-08-02T13:57:45.462000","instant":false,"timeserieslabels":["dump_event"]},"id":"4nsHf2owBU","from_name":"phase","to_name":"ts","type":"timeserieslabels","origin":"manual"},{"value":{"start":"2025-08-02T14:02:41.304000","end":"2025-08-02T14:10:54.330000","instant":false,"timeserieslabels":["load_event"]},"id":"tjx5liIeZL","from_name":"phase","to_name":"ts","type":"timeserieslabels","origin":"manual"},{"value":{"start":"2025-08-02T14:20:08.975000","end":"2025-08-02T14:21:59.605000","instant":false,"timeserieslabels":["dump_event"]},"id":"uktRVICpem","from_name":"phase","to_name":"ts","type":"timeserieslabels","origin":"manual"},{"value":{"start":"2025-08-02T14:32:28.310000","end":"2025-08-02T14:40:41.341000","instant":false,"timeserieslabels":["load_event"]},"id":"2uLUSLLgzJ","from_name":"phase","to_name":"ts","type":"timeserieslabels","origin":"manual"},{"value":{"start":"2025-08-02T14:50:07.987000","end":"2025-08-02T14:52:23.646000","instant":false,"timeserieslabels":["dump_event"]},"id":"u72l7EGd0E","from_name":"phase","to_name":"ts","type":"timeserieslabels","origin":"manual"},{"value":{"start":"2025-08-02T15:00:21.726000","end":"2025-08-02T15:09:23.833000","instant":false,"timeserieslabels":["load_event"]},"id":"TKIcg7WHO4","from_name":"phase","to_name":"ts","type":"timeserieslabels","origin":"manual"},{"value":{"start":"2025-08-02T15:18:13.953000","end":"2025-08-02T15:20:04.579000","instant":false,"timeserieslabels":["dump_event"]},"id":"9pblP5V5qV","from_name":"phase","to_name":"ts","type":"timeserieslabels","origin":"manual"},{"value":{"start":"2025-08-02T15:31:22.364000","end":"2025-08-02T15:38:58.363000","instant":false,"timeserieslabels":["load_event"]},"id":"MJMCEvu0iR","from_name":"phase","to_name":"ts","type":"timeserieslabels","origin":"manual"},{"value":{"start":"2025-08-02T15:44:55.771000","end":"2025-08-02T15:46:58.901000","instant":false,"timeserieslabels":["dump_event"]},"id":"weOyK6uSd0","from_name":"phase","to_name":"ts","type":"timeserieslabels","origin":"manual"},{"value":{"start":"2025-08-02T15:56:01.516000","end":"2025-08-02T16:04:39.111000","instant":false,"timeserieslabels":["load_event"]},"id":"o5Zicwukdn","from_name":"phase","to_name":"ts","type":"timeserieslabels","origin":"manual"},{"value":{"start":"2025-08-02T16:15:44.380000","end":"2025-08-02T16:18:37.079000","instant":false,"timeserieslabels":["dump_event"]},"id":"-nO3c0rh5k","from_name":"phase","to_name":"ts","type":"timeserieslabels","origin":"manual"},{"value":{"start":"2025-08-02T16:24:34.469000","end":"2025-08-02T16:31:57.977000","instant":false,"timeserieslabels":["load_event"]},"id":"BfBETMrJXW","from_name":"phase","to_name":"ts","type":"timeserieslabels","origin":"manual"},{"value":{"start":"2025-08-02T16:46:07.988000","end":"2025-08-02T16:47:59.101000","instant":false,"timeserieslabels":["dump_event"]},"id":"RpWCN97q9T","from_name":"phase","to_name":"ts","type":"timeserieslabels","origin":"manual"},{"value":{"start":"2025-08-02T16:53:32.006000","end":"2025-08-02T17:01:20.042000","instant":false,"timeserieslabels":["load_event"]},"id":"2e50z2T2-J","from_name":"phase","to_name":"ts","type":"timeserieslabels","origin":"manual"},{"value":{"start":"2025-08-02T17:12:00.767000","end":"2025-08-02T17:14:53.462000","instant":false,"timeserieslabels":["dump_event"]},"id":"Z95gIvSkft","from_name":"phase","to_name":"ts","type":"timeserieslabels","origin":"manual"},{"value":{"start":"2025-08-02T17:18:23.211000","end":"2025-08-02T17:27:00.815000","instant":false,"timeserieslabels":["load_event"]},"id":"YgNjq8Jhtx","from_name":"phase","to_name":"ts","type":"timeserieslabels","origin":"manual"},{"value":{"start":"2025-08-02T17:34:24.346000","end":"2025-08-02T17:36:40.001000","instant":false,"timeserieslabels":["dump_event"]},"id":"SyE6EG9m16","from_name":"phase","to_name":"ts","type":"timeserieslabels","origin":"manual"},{"value":{"start":"2025-08-02T17:43:13.959000","end":"2025-08-02T17:53:18.144000","instant":false,"timeserieslabels":["load_event"]},"id":"nZfQhGqOWT","from_name":"phase","to_name":"ts","type":"timeserieslabels","origin":"manual"},{"value":{"start":"2025-08-02T17:59:40.101000","end":"2025-08-02T18:02:44.821000","instant":false,"timeserieslabels":["dump_event"]},"id":"swp5dX1cyr","from_name":"phase","to_name":"ts","type":"timeserieslabels","origin":"manual"},{"value":{"start":"2025-08-02T18:19:06.468000","end":"2025-08-02T18:26:17.440000","instant":false,"timeserieslabels":["load_event"]},"id":"IHZeIyx9sY","from_name":"phase","to_name":"ts","type":"timeserieslabels","origin":"manual"},{"value":{"start":"2025-08-02T18:32:02.838000","end":"2025-08-02T18:34:55.034000","instant":false,"timeserieslabels":["dump_event"]},"id":"hLvMfhbNHm","from_name":"phase","to_name":"ts","type":"timeserieslabels","origin":"manual"},{"value":{"start":"2025-08-02T18:43:08.117000","end":"2025-08-02T18:49:05.498000","instant":false,"timeserieslabels":["load_event"]},"id":"-1VH7IRiXo","from_name":"phase","to_name":"ts","type":"timeserieslabels","origin":"manual"},{"value":{"start":"2025-08-02T18:58:57.202000","end":"2025-08-02T19:02:01.910000","instant":false,"timeserieslabels":["dump_event"]},"id":"NdzRnVw5Nf","from_name":"phase","to_name":"ts","type":"timeserieslabels","origin":"manual"},{"value":{"start":"2025-08-02T19:07:22.291000","end":"2025-08-02T19:13:56.742000","instant":false,"timeserieslabels":["load_event"]},"id":"1Ukm7SLykN","from_name":"phase","to_name":"ts","type":"timeserieslabels","origin":"manual"},{"value":{"start":"2025-08-02T19:21:32.778000","end":"2025-08-02T19:24:37.492000","instant":false,"timeserieslabels":["dump_event"]},"id":"E3MM8XLWb8","from_name":"phase","to_name":"ts","type":"timeserieslabels","origin":"manual"},{"value":{"start":"2025-08-02T19:32:00.960000","end":"2025-08-02T19:38:59.946000","instant":false,"timeserieslabels":["load_event"]},"id":"xBTci7TFXV","from_name":"phase","to_name":"ts","type":"timeserieslabels","origin":"manual"},{"value":{"start":"2025-08-02T19:47:37.521000","end":"2025-08-02T19:51:19.283000","instant":false,"timeserieslabels":["dump_event"]},"id":"OKK1o5d-DR","from_name":"phase","to_name":"ts","type":"timeserieslabels","origin":"manual"},{"value":{"start":"2025-08-02T19:59:32.355000","end":"2025-08-02T20:08:22.426000","instant":false,"timeserieslabels":["load_event"]},"id":"ytnUqk7-nj","from_name":"phase","to_name":"ts","type":"timeserieslabels","origin":"manual"},{"value":{"start":"2025-08-02T20:15:58.455000","end":"2025-08-02T20:17:49.087000","instant":false,"timeserieslabels":["dump_event"]},"id":"TyK5nkx6xg","from_name":"phase","to_name":"ts","type":"timeserieslabels","origin":"manual"},{"value":{"start":"2025-08-02T20:25:25.158000","end":"2025-08-02T20:31:47.084000","instant":false,"timeserieslabels":["load_event"]},"id":"HDAb33aFlv","from_name":"phase","to_name":"ts","type":"timeserieslabels","origin":"manual"},{"value":{"start":"2025-08-02T20:36:42.927000","end":"2025-08-02T20:40:49.205000","instant":false,"timeserieslabels":["dump_event"]},"id":"tfLHU_v8ej","from_name":"phase","to_name":"ts","type":"timeserieslabels","origin":"manual"},{"value":{"start":"2025-08-02T20:45:20.530000","end":"2025-08-02T20:52:19.541000","instant":false,"timeserieslabels":["load_event"]},"id":"pq_2uKI_EX","from_name":"phase","to_name":"ts","type":"timeserieslabels","origin":"manual"},{"value":{"start":"2025-08-02T20:59:18.511000","end":"2025-08-02T21:01:34.165000","instant":false,"timeserieslabels":["dump_event"]},"id":"UmzZwb5CZ7","from_name":"phase","to_name":"ts","type":"timeserieslabels","origin":"manual"},{"value":{"start":"2025-08-02T21:06:42.018000","end":"2025-08-02T21:13:28.978000","instant":false,"timeserieslabels":["load_event"]},"id":"F7lXCrl7p-","from_name":"phase","to_name":"ts","type":"timeserieslabels","origin":"manual"},{"value":{"start":"2025-08-02T21:19:50.933000","end":"2025-08-02T21:21:41.549000","instant":false,"timeserieslabels":["dump_event"]},"id":"L1VxrY8IbH","from_name":"phase","to_name":"ts","type":"timeserieslabels","origin":"manual"},{"value":{"start":"2025-08-02T21:28:53.050000","end":"2025-08-02T21:36:16.554000","instant":false,"timeserieslabels":["load_event"]},"id":"eLRQ-4jHDe","from_name":"phase","to_name":"ts","type":"timeserieslabels","origin":"manual"},{"value":{"start":"2025-08-02T21:48:39.883000","end":"2025-08-02T21:51:32.583000","instant":false,"timeserieslabels":["dump_event"]},"id":"l6DilaWpGj","from_name":"phase","to_name":"ts","type":"timeserieslabels","origin":"manual"},{"value":{"start":"2025-08-02T21:57:04.996000","end":"2025-08-02T22:04:16.477000","instant":false,"timeserieslabels":["load_event"]},"id":"Hlcwd6F2Md","from_name":"phase","to_name":"ts","type":"timeserieslabels","origin":"manual"},{"value":{"start":"2025-08-02T22:09:36.832000","end":"2025-08-02T22:11:52.496000","instant":false,"timeserieslabels":["dump_event"]},"id":"RilLwLwms6","from_name":"phase","to_name":"ts","type":"timeserieslabels","origin":"manual"},{"value":{"start":"2025-08-02T22:19:03.504000","end":"2025-08-02T22:27:29.106000","instant":false,"timeserieslabels":["load_event"]},"id":"CQJtkUp5SC","from_name":"phase","to_name":"ts","type":"timeserieslabels","origin":"manual"},{"value":{"start":"2025-08-02T22:37:32.807000","end":"2025-08-02T22:40:50.026000","instant":false,"timeserieslabels":["dump_event"]},"id":"uE2ilorOa1","from_name":"phase","to_name":"ts","type":"timeserieslabels","origin":"manual"}],"was_cancelled":false,"ground_truth":false,"created_at":"2025-08-28T00:37:15.629416Z","updated_at":"2025-08-28T00:37:15.629433Z","draft_created_at":"2025-08-28T00:34:05.522823Z","lead_time":206.383,"prediction":{},"result_count":48,"unique_id":"3af934ce-dca2-4f85-ac2e-4fa7833ea1ef","import_id":null,"last_action":null,"bulk_created":false,"task":9,"project":13,"updated_by":1,"parent_prediction":null,"parent_annotation":null,"last_created_by":null}],"file_upload":"971d6fbd-lake-605-10-0050_2025-08-02_task.json","drafts":[],"predictions":[],"data":{"truck_id":"lake-605-10-0050","date":"2025-08-02","csv_url":"\/data\/upload\/13\/b8e75868-lake-605-10-0050_2025-08-02.csv"},"meta":{},"created_at":"2025-08-28T00:33:14.689712Z","updated_at":"2025-08-28T00:37:15.686760Z","inner_id":9,"total_annotations":1,"cancelled_annotations":0,"total_predictions":0,"comment_count":0,"unresolved_comment_count":0,"last_comment_updated_at":null,"project":13,"updated_by":1,"comment_authors":[]},{"id":10,"annotations":[{"id":5,"completed_by":1,"result":[{"value":{"start":"2025-08-03T12:20:35.182000","end":"2025-08-03T12:23:59.910000","instant":false,"timeserieslabels":["load_event"]},"id":"Z8wGjHR2Vi","from_name":"phase","to_name":"ts","type":"timeserieslabels","origin":"manual"},{"value":{"start":"2025-08-03T12:29:21.797000","end":"2025-08-03T12:31:09.424000","instant":false,"timeserieslabels":["dump_event"]},"id":"Hitlwlpxu3","from_name":"phase","to_name":"ts","type":"timeserieslabels","origin":"manual"},{"value":{"start":"2025-08-03T12:40:06.078000","end":"2025-08-03T12:44:19.860000","instant":false,"timeserieslabels":["load_event"]},"id":"bDHBGWy6Ic","from_name":"phase","to_name":"ts","type":"timeserieslabels","origin":"manual"},{"value":{"start":"2025-08-03T12:52:37.438000","end":"2025-08-03T12:57:01.248000","instant":false,"timeserieslabels":["dump_event"]},"id":"Dm-Jr3Lv8o","from_name":"phase","to_name":"ts","type":"timeserieslabels","origin":"manual"},{"value":{"start":"2025-08-03T13:00:45.505000","end":"2025-08-03T13:09:03.066000","instant":false,"timeserieslabels":["load_event"]},"id":"sgnp8JdUrd","from_name":"phase","to_name":"ts","type":"timeserieslabels","origin":"manual"},{"value":{"start":"2025-08-03T13:23:12.057000","end":"2025-08-03T13:27:16.360000","instant":false,"timeserieslabels":["dump_event"]},"id":"ZEWfL1DZzz","from_name":"phase","to_name":"ts","type":"timeserieslabels","origin":"manual"},{"value":{"start":"2025-08-03T13:39:47.744000","end":"2025-08-03T13:45:09.624000","instant":false,"timeserieslabels":["load_event"]},"id":"ctOQPtZDKM","from_name":"phase","to_name":"ts","type":"timeserieslabels","origin":"manual"},{"value":{"start":"2025-08-03T13:52:29.154000","end":"2025-08-03T13:54:45.323000","instant":false,"timeserieslabels":["dump_event"]},"id":"CjeZZvHWWd","from_name":"phase","to_name":"ts","type":"timeserieslabels","origin":"manual"},{"value":{"start":"2025-08-03T14:05:57.581000","end":"2025-08-03T14:10:50.447000","instant":false,"timeserieslabels":["load_event"]},"id":"KLvfZgnKmm","from_name":"phase","to_name":"ts","type":"timeserieslabels","origin":"manual"},{"value":{"start":"2025-08-03T14:17:59.933000","end":"2025-08-03T14:20:16.615000","instant":false,"timeserieslabels":["dump_event"]},"id":"YKgXdLW8gD","from_name":"phase","to_name":"ts","type":"timeserieslabels","origin":"manual"},{"value":{"start":"2025-08-03T14:29:52.299000","end":"2025-08-03T14:34:06.091000","instant":false,"timeserieslabels":["load_event"]},"id":"9XdWTEgXTh","from_name":"phase","to_name":"ts","type":"timeserieslabels","origin":"manual"},{"value":{"start":"2025-08-03T14:41:05.547000","end":"2025-08-03T14:43:12.681000","instant":false,"timeserieslabels":["dump_event"]},"id":"nPSEUD5Yi6","from_name":"phase","to_name":"ts","type":"timeserieslabels","origin":"manual"},{"value":{"start":"2025-08-03T14:52:38.842000","end":"2025-08-03T14:57:02.147000","instant":false,"timeserieslabels":["load_event"]},"id":"O5ZohFAV4e","from_name":"phase","to_name":"ts","type":"timeserieslabels","origin":"manual"},{"value":{"start":"2025-08-03T15:09:04.475000","end":"2025-08-03T15:11:21.122000","instant":false,"timeserieslabels":["dump_event"]},"id":"vFogG7BEEd","from_name":"phase","to_name":"ts","type":"timeserieslabels","origin":"manual"},{"value":{"start":"2025-08-03T15:18:30.634000","end":"2025-08-03T15:22:53.953000","instant":false,"timeserieslabels":["load_event"]},"id":"1MYCUWd-Fd","from_name":"phase","to_name":"ts","type":"timeserieslabels","origin":"manual"},{"value":{"start":"2025-08-03T15:29:24.389000","end":"2025-08-03T15:31:50.574000","instant":false,"timeserieslabels":["dump_event"]},"id":"2wr2VJr124","from_name":"phase","to_name":"ts","type":"timeserieslabels","origin":"manual"},{"value":{"start":"2025-08-03T15:39:44.124000","end":"2025-08-03T15:44:36.941000","instant":false,"timeserieslabels":["load_event"]},"id":"CqgaS4-RdE","from_name":"phase","to_name":"ts","type":"timeserieslabels","origin":"manual"},{"value":{"start":"2025-08-03T16:01:51.715000","end":"2025-08-03T16:05:25.983000","instant":false,"timeserieslabels":["dump_event"]},"id":"UuTJ6CaU7B","from_name":"phase","to_name":"ts","type":"timeserieslabels","origin":"manual"},{"value":{"start":"2025-08-03T16:09:59.310000","end":"2025-08-03T16:14:52.125000","instant":false,"timeserieslabels":["load_event"]},"id":"foXrqhlqj9","from_name":"phase","to_name":"ts","type":"timeserieslabels","origin":"manual"},{"value":{"start":"2025-08-03T16:24:47.327000","end":"2025-08-03T16:27:13.992000","instant":false,"timeserieslabels":["dump_event"]},"id":"8K8iTyVT42","from_name":"phase","to_name":"ts","type":"timeserieslabels","origin":"manual"},{"value":{"start":"2025-08-03T16:37:57.790000","end":"2025-08-03T16:43:20.153000","instant":false,"timeserieslabels":["load_event"]},"id":"CM73pDLjsM","from_name":"phase","to_name":"ts","type":"timeserieslabels","origin":"manual"},{"value":{"start":"2025-08-03T16:49:01.561000","end":"2025-08-03T16:50:39.172000","instant":false,"timeserieslabels":["dump_event"]},"id":"4WexfDxxmn","from_name":"phase","to_name":"ts","type":"timeserieslabels","origin":"manual"},{"value":{"start":"2025-08-03T17:00:24.880000","end":"2025-08-03T17:06:16.271000","instant":false,"timeserieslabels":["load_event"]},"id":"wsT__OO0zJ","from_name":"phase","to_name":"ts","type":"timeserieslabels","origin":"manual"},{"value":{"start":"2025-08-03T17:11:28.626000","end":"2025-08-03T17:13:25.754000","instant":false,"timeserieslabels":["dump_event"]},"id":"eQ1Xz6MvNb","from_name":"phase","to_name":"ts","type":"timeserieslabels","origin":"manual"},{"value":{"start":"2025-08-03T17:34:01.661000","end":"2025-08-03T17:40:51.641000","instant":false,"timeserieslabels":["load_event"]},"id":"jMH9xCWs6m","from_name":"phase","to_name":"ts","type":"timeserieslabels","origin":"manual"},{"value":{"start":"2025-08-03T17:47:22.130000","end":"2025-08-03T17:48:40.219000","instant":false,"timeserieslabels":["dump_event"]},"id":"5OyPQ3c0PR","from_name":"phase","to_name":"ts","type":"timeserieslabels","origin":"manual"},{"value":{"start":"2025-08-03T18:01:50.607000","end":"2025-08-03T18:07:12.499000","instant":false,"timeserieslabels":["load_event"]},"id":"R_S88UjzE_","from_name":"phase","to_name":"ts","type":"timeserieslabels","origin":"manual"},{"value":{"start":"2025-08-03T18:13:52.972000","end":"2025-08-03T18:15:40.080000","instant":false,"timeserieslabels":["dump_event"]},"id":"gcGPuWi-KL","from_name":"phase","to_name":"ts","type":"timeserieslabels","origin":"manual"},{"value":{"start":"2025-08-03T18:28:21.502000","end":"2025-08-03T18:32:35.289000","instant":false,"timeserieslabels":["load_event"]},"id":"OoVWFhdRjT","from_name":"phase","to_name":"ts","type":"timeserieslabels","origin":"manual"},{"value":{"start":"2025-08-03T18:40:42.842000","end":"2025-08-03T18:42:10.934000","instant":false,"timeserieslabels":["dump_event"]},"id":"IqYuVei3yk","from_name":"phase","to_name":"ts","type":"timeserieslabels","origin":"manual"},{"value":{"start":"2025-08-03T18:49:00.915000","end":"2025-08-03T18:53:43.761000","instant":false,"timeserieslabels":["load_event"]},"id":"Kc37pD4NiG","from_name":"phase","to_name":"ts","type":"timeserieslabels","origin":"manual"},{"value":{"start":"2025-08-03T19:01:51.806000","end":"2025-08-03T19:03:48.940000","instant":false,"timeserieslabels":["dump_event"]},"id":"uHbJn606qo","from_name":"phase","to_name":"ts","type":"timeserieslabels","origin":"manual"},{"value":{"start":"2025-08-03T19:09:20.835000","end":"2025-08-03T19:18:17.460000","instant":false,"timeserieslabels":["load_event"]},"id":"_Nz9ZdJnRG","from_name":"phase","to_name":"ts","type":"timeserieslabels","origin":"manual"},{"value":{"start":"2025-08-03T19:25:46.456000","end":"2025-08-03T19:28:51.672000","instant":false,"timeserieslabels":["dump_event"]},"id":"bTUKUWbCFN","from_name":"phase","to_name":"ts","type":"timeserieslabels","origin":"manual"},{"value":{"start":"2025-08-03T19:37:58.318000","end":"2025-08-03T19:42:12.103000","instant":false,"timeserieslabels":["load_event"]},"id":"89DP3gcRMg","from_name":"phase","to_name":"ts","type":"timeserieslabels","origin":"manual"},{"value":{"start":"2025-08-03T19:48:42.546000","end":"2025-08-03T19:50:00.635000","instant":false,"timeserieslabels":["dump_event"]},"id":"WzokYICG28","from_name":"phase","to_name":"ts","type":"timeserieslabels","origin":"manual"},{"value":{"start":"2025-08-03T19:57:53.672000","end":"2025-08-03T20:02:46.520000","instant":false,"timeserieslabels":["load_event"]},"id":"ucSyogbT0z","from_name":"phase","to_name":"ts","type":"timeserieslabels","origin":"manual"},{"value":{"start":"2025-08-03T20:09:36.489000","end":"2025-08-03T20:11:14.099000","instant":false,"timeserieslabels":["dump_event"]},"id":"foa3QLxKdl","from_name":"phase","to_name":"ts","type":"timeserieslabels","origin":"manual"},{"value":{"start":"2025-08-03T20:17:54.056000","end":"2025-08-03T20:21:38.804000","instant":false,"timeserieslabels":["load_event"]},"id":"iKmAgdvASS","from_name":"phase","to_name":"ts","type":"timeserieslabels","origin":"manual"},{"value":{"start":"2025-08-03T20:28:38.296000","end":"2025-08-03T20:30:25.417000","instant":false,"timeserieslabels":["dump_event"]},"id":"sM3gPz5Id1","from_name":"phase","to_name":"ts","type":"timeserieslabels","origin":"manual"},{"value":{"start":"2025-08-03T20:39:12.514000","end":"2025-08-03T20:44:15.352000","instant":false,"timeserieslabels":["load_event"]},"id":"vNFS4usRGt","from_name":"phase","to_name":"ts","type":"timeserieslabels","origin":"manual"},{"value":{"start":"2025-08-03T20:50:45.336000","end":"2025-08-03T20:53:12.017000","instant":false,"timeserieslabels":["dump_event"]},"id":"hGpxGgjqbd","from_name":"phase","to_name":"ts","type":"timeserieslabels","origin":"manual"},{"value":{"start":"2025-08-03T21:00:21.512000","end":"2025-08-03T21:08:19.563000","instant":false,"timeserieslabels":["load_event"]},"id":"qJ3oBnYk3C","from_name":"phase","to_name":"ts","type":"timeserieslabels","origin":"manual"},{"value":{"start":"2025-08-03T21:15:19.036000","end":"2025-08-03T21:17:06.649000","instant":false,"timeserieslabels":["dump_event"]},"id":"G098Q6dAFK","from_name":"phase","to_name":"ts","type":"timeserieslabels","origin":"manual"},{"value":{"start":"2025-08-03T21:25:43.789000","end":"2025-08-03T21:31:35.183000","instant":false,"timeserieslabels":["load_event"]},"id":"w6hN5QETna","from_name":"phase","to_name":"ts","type":"timeserieslabels","origin":"manual"},{"value":{"start":"2025-08-03T21:41:30.349000","end":"2025-08-03T21:43:37.009000","instant":false,"timeserieslabels":["dump_event"]},"id":"85ymQrIo-J","from_name":"phase","to_name":"ts","type":"timeserieslabels","origin":"manual"}],"was_cancelled":false,"ground_truth":false,"created_at":"2025-08-28T00:40:03.557557Z","updated_at":"2025-08-28T00:40:03.557571Z","draft_created_at":"2025-08-28T00:37:33.385868Z","lead_time":164.321,"prediction":{},"result_count":46,"unique_id":"17e52863-cb48-4bbc-9b51-c769d59456a6","import_id":null,"last_action":null,"bulk_created":false,"task":10,"project":13,"updated_by":1,"parent_prediction":null,"parent_annotation":null,"last_created_by":null}],"file_upload":"61f5304e-lake-605-10-0050_2025-08-03_task.json","drafts":[],"predictions":[],"data":{"truck_id":"lake-605-10-0050","date":"2025-08-03","csv_url":"\/data\/upload\/13\/2526f020-lake-605-10-0050_2025-08-03.csv"},"meta":{},"created_at":"2025-08-28T00:33:14.689758Z","updated_at":"2025-08-28T00:40:03.642169Z","inner_id":10,"total_annotations":1,"cancelled_annotations":0,"total_predictions":0,"comment_count":0,"unresolved_comment_count":0,"last_comment_updated_at":null,"project":13,"updated_by":1,"comment_authors":[]},{"id":12,"annotations":[{"id":6,"completed_by":1,"result":[{"value":{"start":"2025-08-05T12:30:22.657000","end":"2025-08-05T12:34:55.459000","instant":false,"timeserieslabels":["load_event"]},"id":"65TP3TYGvU","from_name":"phase","to_name":"ts","type":"timeserieslabels","origin":"manual"},{"value":{"start":"2025-08-05T12:52:11.636000","end":"2025-08-05T12:54:33.317000","instant":false,"timeserieslabels":["dump_event"]},"id":"YUVPxL-5at","from_name":"phase","to_name":"ts","type":"timeserieslabels","origin":"manual"},{"value":{"start":"2025-08-05T13:03:38.971000","end":"2025-08-05T13:11:39.057000","instant":false,"timeserieslabels":["load_event"]},"id":"W1RjzSXx6e","from_name":"phase","to_name":"ts","type":"timeserieslabels","origin":"manual"},{"value":{"start":"2025-08-05T13:17:16.950000","end":"2025-08-05T13:18:44.041000","instant":false,"timeserieslabels":["dump_event"]},"id":"DTqiDeGDpW","from_name":"phase","to_name":"ts","type":"timeserieslabels","origin":"manual"},{"value":{"start":"2025-08-05T13:28:22.199000","end":"2025-08-05T13:36:00.705000","instant":false,"timeserieslabels":["load_event"]},"id":"SCPNCePzJi","from_name":"phase","to_name":"ts","type":"timeserieslabels","origin":"manual"},{"value":{"start":"2025-08-05T13:49:38.614000","end":"2025-08-05T13:52:22.321000","instant":false,"timeserieslabels":["dump_event"]},"id":"DFiNV3kTzq","from_name":"phase","to_name":"ts","type":"timeserieslabels","origin":"manual"},{"value":{"start":"2025-08-05T14:05:27.748000","end":"2025-08-05T14:14:22.363000","instant":false,"timeserieslabels":["load_event"]},"id":"Ojz2NMZazn","from_name":"phase","to_name":"ts","type":"timeserieslabels","origin":"manual"},{"value":{"start":"2025-08-05T14:19:27.711000","end":"2025-08-05T14:21:27.842000","instant":false,"timeserieslabels":["dump_event"]},"id":"HpHBUvuGKb","from_name":"phase","to_name":"ts","type":"timeserieslabels","origin":"manual"},{"value":{"start":"2025-08-05T14:26:22.210000","end":"2025-08-05T14:30:21.990000","instant":false,"timeserieslabels":["load_event"]},"id":"U-6SMkzPEf","from_name":"phase","to_name":"ts","type":"timeserieslabels","origin":"manual"},{"value":{"start":"2025-08-05T14:36:32.910000","end":"2025-08-05T14:38:33.061000","instant":false,"timeserieslabels":["dump_event"]},"id":"BdAM6fNvni","from_name":"phase","to_name":"ts","type":"timeserieslabels","origin":"manual"},{"value":{"start":"2025-08-05T14:43:27.409000","end":"2025-08-05T14:47:27.686000","instant":false,"timeserieslabels":["load_event"]},"id":"J4tKQRo8kN","from_name":"phase","to_name":"ts","type":"timeserieslabels","origin":"manual"},{"value":{"start":"2025-08-05T15:37:53.097000","end":"2025-08-05T15:41:09.323000","instant":false,"timeserieslabels":["dump_event"]},"id":"_snkT6gcM7","from_name":"phase","to_name":"ts","type":"timeserieslabels","origin":"manual"},{"value":{"start":"2025-08-05T15:48:25.832000","end":"2025-08-05T15:54:25.747000","instant":false,"timeserieslabels":["load_event"]},"id":"tWV3fTPYk5","from_name":"phase","to_name":"ts","type":"timeserieslabels","origin":"manual"},{"value":{"start":"2025-08-05T15:59:42.134000","end":"2025-08-05T16:02:36.343000","instant":false,"timeserieslabels":["dump_event"]},"id":"NrDhsrHN5T","from_name":"phase","to_name":"ts","type":"timeserieslabels","origin":"manual"},{"value":{"start":"2025-08-05T16:07:52.703000","end":"2025-08-05T16:15:31.245000","instant":false,"timeserieslabels":["load_event"]},"id":"gUbHa733m2","from_name":"phase","to_name":"ts","type":"timeserieslabels","origin":"manual"},{"value":{"start":"2025-08-05T16:21:09.114000","end":"2025-08-05T16:23:19.765000","instant":false,"timeserieslabels":["dump_event"]},"id":"4fOkECHu7W","from_name":"phase","to_name":"ts","type":"timeserieslabels","origin":"manual"},{"value":{"start":"2025-08-05T16:30:36.278000","end":"2025-08-05T16:38:14.783000","instant":false,"timeserieslabels":["load_event"]},"id":"a0RqoELYLR","from_name":"phase","to_name":"ts","type":"timeserieslabels","origin":"manual"},{"value":{"start":"2025-08-05T16:45:09.283000","end":"2025-08-05T16:46:36.379000","instant":false,"timeserieslabels":["dump_event"]},"id":"wLeks0Sx9T","from_name":"phase","to_name":"ts","type":"timeserieslabels","origin":"manual"},{"value":{"start":"2025-08-05T16:54:47.432000","end":"2025-08-05T17:00:58.355000","instant":false,"timeserieslabels":["load_event"]},"id":"cPho-QO0WX","from_name":"phase","to_name":"ts","type":"timeserieslabels","origin":"manual"},{"value":{"start":"2025-08-05T17:23:38.869000","end":"2025-08-05T17:25:16.977000","instant":false,"timeserieslabels":["dump_event"]},"id":"S5ZWiY7UPE","from_name":"phase","to_name":"ts","type":"timeserieslabels","origin":"manual"},{"value":{"start":"2025-08-05T17:34:11.577000","end":"2025-08-05T17:42:00.610000","instant":false,"timeserieslabels":["load_event"]},"id":"37ApNkjGnw","from_name":"phase","to_name":"ts","type":"timeserieslabels","origin":"manual"},{"value":{"start":"2025-08-05T17:48:00.568000","end":"2025-08-05T17:50:00.719000","instant":false,"timeserieslabels":["dump_event"]},"id":"OUPfvc3gdt","from_name":"phase","to_name":"ts","type":"timeserieslabels","origin":"manual"},{"value":{"start":"2025-08-05T17:58:54.898000","end":"2025-08-05T18:05:27.858000","instant":false,"timeserieslabels":["load_event"]},"id":"8OVob1gPLb","from_name":"phase","to_name":"ts","type":"timeserieslabels","origin":"manual"},{"value":{"start":"2025-08-05T18:13:05.893000","end":"2025-08-05T18:14:33.493000","instant":false,"timeserieslabels":["dump_event"]},"id":"6gbz8Og_7B","from_name":"phase","to_name":"ts","type":"timeserieslabels","origin":"manual"},{"value":{"start":"2025-08-05T18:24:22.185000","end":"2025-08-05T18:30:55.145000","instant":false,"timeserieslabels":["load_event"]},"id":"f3WyGzOsfL","from_name":"phase","to_name":"ts","type":"timeserieslabels","origin":"manual"},{"value":{"start":"2025-08-05T18:45:16.632000","end":"2025-08-05T18:46:44.232000","instant":false,"timeserieslabels":["dump_event"]},"id":"YpbNFoMHex","from_name":"phase","to_name":"ts","type":"timeserieslabels","origin":"manual"},{"value":{"start":"2025-08-05T18:54:00.259000","end":"2025-08-05T18:58:22.070000","instant":false,"timeserieslabels":["load_event"]},"id":"BBbHGVa3xC","from_name":"phase","to_name":"ts","type":"timeserieslabels","origin":"manual"},{"value":{"start":"2025-08-05T19:18:43.984000","end":"2025-08-05T19:20:44.119000","instant":false,"timeserieslabels":["dump_event"]},"id":"O21lW1pvdo","from_name":"phase","to_name":"ts","type":"timeserieslabels","origin":"manual"},{"value":{"start":"2025-08-05T19:30:19.772000","end":"2025-08-05T19:35:46.661000","instant":false,"timeserieslabels":["load_event"]},"id":"LWjdmfQ3dI","from_name":"phase","to_name":"ts","type":"timeserieslabels","origin":"manual"},{"value":{"start":"2025-08-05T19:54:41.507000","end":"2025-08-05T19:56:19.617000","instant":false,"timeserieslabels":["dump_event"]},"id":"8CwjOHjIPT","from_name":"phase","to_name":"ts","type":"timeserieslabels","origin":"manual"},{"value":{"start":"2025-08-05T20:01:57.536000","end":"2025-08-05T20:07:03.377000","instant":false,"timeserieslabels":["load_event"]},"id":"4kMdg1CWEu","from_name":"phase","to_name":"ts","type":"timeserieslabels","origin":"manual"},{"value":{"start":"2025-08-05T20:17:25.091000","end":"2025-08-05T20:20:19.297000","instant":false,"timeserieslabels":["dump_event"]},"id":"bDf8aSmI5O","from_name":"phase","to_name":"ts","type":"timeserieslabels","origin":"manual"},{"value":{"start":"2025-08-05T20:25:35.662000","end":"2025-08-05T20:29:35.928000","instant":false,"timeserieslabels":["load_event"]},"id":"_ND768NXXu","from_name":"phase","to_name":"ts","type":"timeserieslabels","origin":"manual"},{"value":{"start":"2025-08-05T20:48:08.726000","end":"2025-08-05T20:51:35.956000","instant":false,"timeserieslabels":["dump_event"]},"id":"_tUSWhvq5W","from_name":"phase","to_name":"ts","type":"timeserieslabels","origin":"manual"},{"value":{"start":"2025-08-05T20:58:08.461000","end":"2025-08-05T21:02:08.240000","instant":false,"timeserieslabels":["load_event"]},"id":"P-1KMf0q8q","from_name":"phase","to_name":"ts","type":"timeserieslabels","origin":"manual"},{"value":{"start":"2025-08-05T21:08:30.195000","end":"2025-08-05T21:11:24.901000","instant":false,"timeserieslabels":["dump_event"]},"id":"zyUkalVeWN","from_name":"phase","to_name":"ts","type":"timeserieslabels","origin":"manual"},{"value":{"start":"2025-08-05T21:31:13.745000","end":"2025-08-05T21:35:46.566000","instant":false,"timeserieslabels":["load_event"]},"id":"omUyxrTr1x","from_name":"phase","to_name":"ts","type":"timeserieslabels","origin":"manual"},{"value":{"start":"2025-08-05T21:41:02.961000","end":"2025-08-05T21:43:03.099000","instant":false,"timeserieslabels":["dump_event"]},"id":"Nr__vz_uos","from_name":"phase","to_name":"ts","type":"timeserieslabels","origin":"manual"},{"value":{"start":"2025-08-05T21:50:08.097000","end":"2025-08-05T21:55:13.947000","instant":false,"timeserieslabels":["load_event"]},"id":"vIRSJlDR4y","from_name":"phase","to_name":"ts","type":"timeserieslabels","origin":"manual"},{"value":{"start":"2025-08-05T22:11:57.120000","end":"2025-08-05T22:13:57.261000","instant":false,"timeserieslabels":["dump_event"]},"id":"_240Y2sZpS","from_name":"phase","to_name":"ts","type":"timeserieslabels","origin":"manual"},{"value":{"start":"2025-08-05T22:19:35.645000","end":"2025-08-05T22:24:41.004000","instant":false,"timeserieslabels":["load_event"]},"id":"gjqMtzcOJu","from_name":"phase","to_name":"ts","type":"timeserieslabels","origin":"manual"},{"value":{"start":"2025-08-05T22:31:35.507000","end":"2025-08-05T22:33:35.648000","instant":false,"timeserieslabels":["dump_event"]},"id":"ccrPLtKYvF","from_name":"phase","to_name":"ts","type":"timeserieslabels","origin":"manual"},{"value":{"start":"2025-08-05T22:40:41.166000","end":"2025-08-05T22:45:24.489000","instant":false,"timeserieslabels":["load_event"]},"id":"vC6NELWT6Q","from_name":"phase","to_name":"ts","type":"timeserieslabels","origin":"manual"},{"value":{"start":"2025-08-05T22:51:13.887000","end":"2025-08-05T22:53:24.553000","instant":false,"timeserieslabels":["dump_event"]},"id":"G5KvhlBHGT","from_name":"phase","to_name":"ts","type":"timeserieslabels","origin":"manual"}],"was_cancelled":false,"ground_truth":false,"created_at":"2025-08-28T00:43:19.109707Z","updated_at":"2025-08-28T00:43:19.109721Z","draft_created_at":"2025-08-28T00:40:49.162079Z","lead_time":189.836,"prediction":{},"result_count":44,"unique_id":"eae70f24-c8e7-4bfc-9f30-256c7d90e193","import_id":null,"last_action":null,"bulk_created":false,"task":12,"project":13,"updated_by":1,"parent_prediction":null,"parent_annotation":null,"last_created_by":null}],"file_upload":"f0978ca9-lake-605-10-0050_2025-08-05_task.json","drafts":[],"predictions":[],"data":{"truck_id":"lake-605-10-0050","date":"2025-08-05","csv_url":"\/data\/upload\/13\/1fc4c00e-lake-605-10-0050_2025-08-05.csv"},"meta":{},"created_at":"2025-08-28T00:33:14.689819Z","updated_at":"2025-08-28T00:43:19.198714Z","inner_id":12,"total_annotations":1,"cancelled_annotations":0,"total_predictions":0,"comment_count":0,"unresolved_comment_count":0,"last_comment_updated_at":null,"project":13,"updated_by":1,"comment_authors":[]}]